design/memory.sv
`timescale 1ns/1ps

module memory #(
    parameter DATA_WIDTH = 32,
              ADDR_WIDTH = 6,
              NVM_INIT = ""
) (
    input logic clk,
    // protects memory from being written to, on by default
    input logic write_enable,
    input logic [ADDR_WIDTH - 1:0] address,
    input logic [DATA_WIDTH - 1:0] data_in,
    // Kind of like flash sector erase.
    input logic reset,
    output logic [DATA_WIDTH - 1:0] data_out
);

initial begin
    if (NVM_INIT != "") begin
        $readmemh(NVM_INIT, array_reg);
    end
end


logic [DATA_WIDTH - 1 : 0] array_reg [0: 2** ADDR_WIDTH - 1];

always_ff @( posedge clk ) begin
    if (reset == 1'b0) begin
        for (int i = 0; i < 2** ADDR_WIDTH; i++) begin
            array_reg[i] <= 32'd0;
        end
    end
    else if (write_enable)
        array_reg[address] <= data_in;
end

assign data_out = array_reg[address];

endmodule

tb/memory/dump.vcd
$version Generated by VerilatedVcd $end
$timescale 1ps $end
 $scope module $rootio $end
  $var wire 1 # clk $end
  $var wire 1 $ write_enable $end
  $var wire 6 % address [5:0] $end
  $var wire 32 & data_in [31:0] $end
  $var wire 1 ' reset $end
  $var wire 32 ( data_out [31:0] $end
 $upscope $end
 $scope module memory $end
  $var wire 32 0 DATA_WIDTH [31:0] $end
  $var wire 32 1 ADDR_WIDTH [31:0] $end
  $var wire 32 2 NVM_INIT [31:0] $end
  $var wire 1 ) clk $end
  $var wire 1 * write_enable $end
  $var wire 6 + address [5:0] $end
  $var wire 32 , data_in [31:0] $end
  $var wire 1 - reset $end
  $var wire 32 . data_out [31:0] $end
  $scope module unnamedblk1 $end
   $var wire 32 / i [31:0] $end
  $upscope $end
 $upscope $end
$enddefinitions $end


#0
1#
0$
b000000 %
b00000000000000000000000000000000 &
0'
b00000000000000000000000000000000 (
1)
0*
b000000 +
b00000000000000000000000000000000 ,
0-
b00000000000000000000000000000000 .
b00000000000000000000000001000000 /
b00000000000000000000000000100000 0
b00000000000000000000000000000110 1
b00000000000000000000000000000000 2
#500
0#
0)
#1000
1#
1)
#1500
0#
0)
#2000
1#
1'
1)
1-
#2500
0#
0)
#3000
1#
b000001 %
1)
b000001 +
#3500
0#
0)
#4000
1#
b000010 %
1)
b000010 +
#4500
0#
0)
#5000
1#
b000011 %
1)
b000011 +
#5500
0#
0)
#6000
1#
b000100 %
1)
b000100 +
#6500
0#
0)
#7000
1#
b000101 %
1)
b000101 +
#7500
0#
0)
#8000
1#
b000110 %
1)
b000110 +
#8500
0#
0)
#9000
1#
b000111 %
1)
b000111 +
#9500
0#
0)
#10000
1#
b001000 %
1)
b001000 +
#10500
0#
0)
#11000
1#
b001001 %
1)
b001001 +
#11500
0#
0)
#12000
1#
b001010 %
1)
b001010 +
#12500
0#
0)
#13000
1#
b001011 %
1)
b001011 +
#13500
0#
0)
#14000
1#
b001100 %
1)
b001100 +
#14500
0#
0)
#15000
1#
b001101 %
1)
b001101 +
#15500
0#
0)
#16000
1#
b001110 %
1)
b001110 +
#16500
0#
0)
#17000
1#
b001111 %
1)
b001111 +
#17500
0#
0)
#18000
1#
b010000 %
1)
b010000 +
#18500
0#
0)
#19000
1#
b010001 %
1)
b010001 +
#19500
0#
0)
#20000
1#
b010010 %
1)
b010010 +
#20500
0#
0)
#21000
1#
b010011 %
1)
b010011 +
#21500
0#
0)
#22000
1#
b010100 %
1)
b010100 +
#22500
0#
0)
#23000
1#
b010101 %
1)
b010101 +
#23500
0#
0)
#24000
1#
b010110 %
1)
b010110 +
#24500
0#
0)
#25000
1#
b010111 %
1)
b010111 +
#25500
0#
0)
#26000
1#
b011000 %
1)
b011000 +
#26500
0#
0)
#27000
1#
b011001 %
1)
b011001 +
#27500
0#
0)
#28000
1#
b011010 %
1)
b011010 +
#28500
0#
0)
#29000
1#
b011011 %
1)
b011011 +
#29500
0#
0)
#30000
1#
b011100 %
1)
b011100 +
#30500
0#
0)
#31000
1#
b011101 %
1)
b011101 +
#31500
0#
0)
#32000
1#
b011110 %
1)
b011110 +
#32500
0#
0)
#33000
1#
b011111 %
1)
b011111 +
#33500
0#
0)
#34000
1#
b100000 %
1)
b100000 +
#34500
0#
0)
#35000
1#
b100001 %
1)
b100001 +
#35500
0#
0)
#36000
1#
b100010 %
1)
b100010 +
#36500
0#
0)
#37000
1#
b100011 %
1)
b100011 +
#37500
0#
0)
#38000
1#
b100100 %
1)
b100100 +
#38500
0#
0)
#39000
1#
b100101 %
1)
b100101 +
#39500
0#
0)
#40000
1#
b100110 %
1)
b100110 +
#40500
0#
0)
#41000
1#
b100111 %
1)
b100111 +
#41500
0#
0)
#42000
1#
b101000 %
1)
b101000 +
#42500
0#
0)
#43000
1#
b101001 %
1)
b101001 +
#43500
0#
0)
#44000
1#
b101010 %
1)
b101010 +
#44500
0#
0)
#45000
1#
b101011 %
1)
b101011 +
#45500
0#
0)
#46000
1#
b101100 %
1)
b101100 +
#46500
0#
0)
#47000
1#
b101101 %
1)
b101101 +
#47500
0#
0)
#48000
1#
b101110 %
1)
b101110 +
#48500
0#
0)
#49000
1#
b101111 %
1)
b101111 +
#49500
0#
0)
#50000
1#
b110000 %
1)
b110000 +
#50500
0#
0)
#51000
1#
b110001 %
1)
b110001 +
#51500
0#
0)
#52000
1#
b110010 %
1)
b110010 +
#52500
0#
0)
#53000
1#
b110011 %
1)
b110011 +
#53500
0#
0)
#54000
1#
b110100 %
1)
b110100 +
#54500
0#
0)
#55000
1#
b110101 %
1)
b110101 +
#55500
0#
0)
#56000
1#
b110110 %
1)
b110110 +
#56500
0#
0)
#57000
1#
b110111 %
1)
b110111 +
#57500
0#
0)
#58000
1#
b111000 %
1)
b111000 +
#58500
0#
0)
#59000
1#
b111001 %
1)
b111001 +
#59500
0#
0)
#60000
1#
b111010 %
1)
b111010 +
#60500
0#
0)
#61000
1#
b111011 %
1)
b111011 +
#61500
0#
0)
#62000
1#
b111100 %
1)
b111100 +
#62500
0#
0)
#63000
1#
b111101 %
1)
b111101 +
#63500
0#
0)
#64000
1#
b111110 %
1)
b111110 +
#64500
0#
0)
#65000
1#
b111111 %
1)
b111111 +
#65500
0#
0)
#66000
1#
b000000 %
b11011110101011011011111011101111 &
b11011110101011011011111011101111 (
1)
b000000 +
b11011110101011011011111011101111 ,
b11011110101011011011111011101111 .
#66500
0#
0)
#67000
1#
1)
#67500
0#
0)
#68000
1#
1$
b000100 %
b11001010111111101011101010111110 &
b00000000000000000000000000000000 (
1)
1*
b000100 +
b11001010111111101011101010111110 ,
b00000000000000000000000000000000 .
#68500
0#
0)
#69000
1#
0$
b11001010111111101011101010111110 (
1)
0*
b11001010111111101011101010111110 .
#69500
0#
0)
#70000
1#
1)
#70500
0#
0)
#71000
1#
1$
b001000 %
b00010010001101000101011001111000 &
b00000000000000000000000000000000 (
1)
1*
b001000 +
b00010010001101000101011001111000 ,
b00000000000000000000000000000000 .
#71500
0#
0)
#72000
1#
0$
b00010010001101000101011001111000 (
1)
0*
b00010010001101000101011001111000 .
#72500
0#
0)
#73000
1#
1)
#73500
0#
0)
#74000
1#
1$
b001100 %
b10100101101001011010010110100101 &
b00000000000000000000000000000000 (
1)
1*
b001100 +
b10100101101001011010010110100101 ,
b00000000000000000000000000000000 .
#74500
0#
0)
#75000
1#
0$
b10100101101001011010010110100101 (
1)
0*
b10100101101001011010010110100101 .
