design/alu.sv
`timescale 1ns/1ps

module alu (
    input logic [31:0] alu_control,
    input logic [31:0] operand1,
    input logic [31:0] operand2,
    input logic [4:0] shamt,

    output logic [31:0] alu_result
);

typedef enum {ALU_ADD, ALU_SUB, ALU_AND, ALU_OR, ALU_XOR} alu_control_t;

wire logic [4:0] shamt = operand2[4:0];

always_comb begin
    case (alu_control)
        // ADD STUFF
        ALU_ADD : alu_result = operand1 + operand2;
        ALU_SUB : alu_result = operand1 + (~operand2 + 1'b1);
        ALU_AND : alu_result = operand1 & operand2;
        ALU_OR : alu_result = operand1 | operand2;
        ALU_XOR : alu_result = operand1 ^ operand2;
        default : alu_result = 32'd0;
    endcase
end
    
endmodule

tb/alu/dump.vcd
$version Generated by VerilatedVcd $end
$timescale 1ps $end
 $scope module $rootio $end
  $var wire 32 # alu_control [31:0] $end
  $var wire 32 $ operand1 [31:0] $end
  $var wire 32 % operand2 [31:0] $end
  $var wire 32 & alu_result [31:0] $end
 $upscope $end
 $scope module alu $end
  $var wire 32 ' alu_control [31:0] $end
  $var wire 32 ( operand1 [31:0] $end
  $var wire 32 ) operand2 [31:0] $end
  $var wire 32 * alu_result [31:0] $end
  $var wire 5 + shamt [4:0] $end
 $upscope $end
$enddefinitions $end


#0
b00000000000000000000000000000000 #
b00000000000000000000000000000000 $
b00000000000000000000000000000000 %
b00000000000000000000000000000000 &
b00000000000000000000000000000000 '
b00000000000000000000000000000000 (
b00000000000000000000000000000000 )
b00000000000000000000000000000000 *
b00000 +
#1000
b00111111101000010100111001000111 $
b10000111010100000010011010000110 %
b11000110111100010111010011001101 &
b00111111101000010100111001000111 (
b10000111010100000010011010000110 )
b11000110111100010111010011001101 *
b00110 +
#2000
b11010011001100010000110100001111 $
b00101011001111000100100010111010 %
b11111110011011010101010111001001 &
b11010011001100010000110100001111 (
b00101011001111000100100010111010 )
b11111110011011010101010111001001 *
b11010 +
#3000
b01100011000000111110000110110100 $
b00011010011000001100010101011111 %
b01111101011001001010011100010011 &
b01100011000000111110000110110100 (
b00011010011000001100010101011111 )
b01111101011001001010011100010011 *
b11111 +
#4000
b00001101110100010010000100111000 $
b00101001010101001100011110001110 %
b00110111001001011110100011000110 &
b00001101110100010010000100111000 (
b00101001010101001100011110001110 )
b00110111001001011110100011000110 *
b01110 +
#5000
b00101110111001101111110001011110 $
b10101011100110011110110011100011 %
b11011010100000001110100101000001 &
b00101110111001101111110001011110 (
b10101011100110011110110011100011 )
b11011010100000001110100101000001 *
b00011 +
#6000
b11010110001011101111000001100010 $
b00011101001100101001000011010111 %
b11110011011000011000000100111001 &
b11010110001011101111000001100010 (
b00011101001100101001000011010111 )
b11110011011000011000000100111001 *
b10111 +
#7000
b10010101011100111100101010101101 $
b11011001011100000001011001001001 %
b01101110111000111110000011110110 &
b10010101011100111100101010101101 (
b11011001011100000001011001001001 )
b01101110111000111110000011110110 *
b01001 +
#8000
b11010011110110110010111111000000 $
b11001110010011001011100001110001 %
b10100010001001111110100000110001 &
b11010011110110110010111111000000 (
b11001110010011001011100001110001 )
b10100010001001111110100000110001 *
b10001 +
#9000
b00100001000011000001000101100111 $
b11111010001011111100001011100011 %
b00011011001110111101010001001010 &
b00100001000011000001000101100111 (
b11111010001011111100001011100011 )
b00011011001110111101010001001010 *
b00011 +
#10000
b01101111000110111000101001010100 $
b10110011000101111100110011111101 %
b00100010001100110101011101010001 &
b01101111000110111000101001010100 (
b10110011000101111100110011111101 )
b00100010001100110101011101010001 *
b11101 +
#11000
b01100110110010011011101111111111 $
b01011001001001100110110000001000 %
b10111111111100000010100000000111 &
b01100110110010011011101111111111 (
b01011001001001100110110000001000 )
b10111111111100000010100000000111 *
b01000 +
#12000
b01011100001100100011010011000001 $
b01001100101111100100001101011100 %
b10101000111100000111100000011101 &
b01011100001100100011010011000001 (
b01001100101111100100001101011100 )
b10101000111100000111100000011101 *
b11100 +
#13000
b10100100011110111100011110101010 $
b10110010101111110011100010010100 %
b01010111001110110000000000111110 &
b10100100011110111100011110101010 (
b10110010101111110011100010010100 )
b01010111001110110000000000111110 *
b10100 +
#14000
b11000100010011101011110010111000 $
b00111010011001011110110011100100 %
b11111110101101001010100110011100 &
b11000100010011101011110010111000 (
b00111010011001011110110011100100 )
b11111110101101001010100110011100 *
b00100 +
#15000
b11011110001001011011101001001000 $
b00100011001010100011101000001111 %
b00000001010011111111010001010111 &
b11011110001001011011101001001000 (
b00100011001010100011101000001111 )
b00000001010011111111010001010111 *
b01111 +
#16000
b00111011010011000101000100010001 $
b01011001000001010101101100111110 %
b10010100010100011010110001001111 &
b00111011010011000101000100010001 (
b01011001000001010101101100111110 )
b10010100010100011010110001001111 *
b11110 +
#17000
b10010110111001111000111000001101 $
b11111110010110011010100111000010 %
b10010101010000010011011111001111 &
b10010110111001111000111000001101 (
b11111110010110011010100111000010 )
b10010101010000010011011111001111 *
b00010 +
#18000
b00111100111101011101100110010100 $
b11110001011010000010001101000010 %
b00101110010111011111110011010110 &
b00111100111101011101100110010100 (
b11110001011010000010001101000010 )
b00101110010111011111110011010110 *
#19000
b00000001100001110100011000001101 $
b01110001100011000111100101010010 %
b01110011000100111011111101011111 &
b00000001100001110100011000001101 (
b01110001100011000111100101010010 )
b01110011000100111011111101011111 *
b10010 +
#20000
b10011001001100000110101001011010 $
b11011001111100111001001100111000 %
b01110011001000111111110110010010 &
b10011001001100000110101001011010 (
b11011001111100111001001100111000 )
b01110011001000111111110110010010 *
b11000 +
#21000
b01011101010011101010001011011001 $
b11001010111111001101010111101011 %
b00101000010010110111100011000100 &
b01011101010011101010001011011001 (
b11001010111111001101010111101011 )
b00101000010010110111100011000100 *
b01011 +
#22000
b00010110010111011111010100110001 $
b00001100011000001001100101010101 %
b00100010101111101000111010000110 &
b00010110010111011111010100110001 (
b00001100011000001001100101010101 )
b00100010101111101000111010000110 *
b10101 +
#23000
b11000101010101100010001000110111 $
b00001001010000010011101011000010 %
b11001110100101110101110011111001 &
b11000101010101100010001000110111 (
b00001001010000010011101011000010 )
b11001110100101110101110011111001 *
b00010 +
#24000
b00000101000001111100010100011110 $
b10010110001000011110100011111010 %
b10011011001010011010111000011000 &
b00000101000001111100010100011110 (
b10010110001000011110100011111010 )
b10011011001010011010111000011000 *
b11010 +
#25000
b00001100111011100011000111010011 $
b10001010001100101110011011001001 %
b10010111001000010001100010011100 &
b00001100111011100011000111010011 (
b10001010001100101110011011001001 )
b10010111001000010001100010011100 *
b01001 +
#26000
b00110101100011010100001000101110 $
b01110110011110000100101011101010 %
b10101100000001011000110100011000 &
b00110101100011010100001000101110 (
b01110110011110000100101011101010 )
b10101100000001011000110100011000 *
b01010 +
#27000
b11100110110010000101000111001011 $
b00100010100111010100011100011010 %
b00001001011001011001100011100101 &
b11100110110010000101000111001011 (
b00100010100111010100011100011010 )
b00001001011001011001100011100101 *
b11010 +
#28000
b10010100011101100100111001100000 $
b11010100110101101000011000011110 %
b01101001010011001101010001111110 &
b10010100011101100100111001100000 (
b11010100110101101000011000011110 )
b01101001010011001101010001111110 *
b11110 +
#29000
b10111010100100111011111011101111 $
b00101110101100001001100001010001 %
b11101001010001000101011101000000 &
b10111010100100111011111011101111 (
b00101110101100001001100001010001 )
b11101001010001000101011101000000 *
b10001 +
#30000
b11011100111101010000111011010011 $
b01100011000000010001000010101001 %
b00111111111101100001111101111100 &
b11011100111101010000111011010011 (
b01100011000000010001000010101001 )
b00111111111101100001111101111100 *
b01001 +
#31000
b01001100000100110111110001010101 $
b00011010100001011111100110110000 %
b01100110100110010111011000000101 &
b01001100000100110111110001010101 (
b00011010100001011111100110110000 )
b01100110100110010111011000000101 *
b10000 +
#32000
b10011101101000001111010111011101 $
b11010010110100100101011010111110 %
b01110000011100110100110010011011 &
b10011101101000001111010111011101 (
b11010010110100100101011010111110 )
b01110000011100110100110010011011 *
b11110 +
#33000
b01001001001101101000001011111011 $
b10110010101101101100000010100010 %
b11111011111011010100001110011101 &
b01001001001101101000001011111011 (
b10110010101101101100000010100010 )
b11111011111011010100001110011101 *
b00010 +
#34000
b01101111011001011001001101100010 $
b00001001111000010101001011011001 %
b01111001010001101110011000111011 &
b01101111011001011001001101100010 (
b00001001111000010101001011011001 )
b01111001010001101110011000111011 *
b11001 +
#35000
b11111001100001111010001000100010 $
b01000110001011010101011000101010 %
b00111111101101001111100001001100 &
b11111001100001111010001000100010 (
b01000110001011010101011000101010 )
b00111111101101001111100001001100 *
b01010 +
#36000
b11000101101111000000001101110111 $
b11111011010100111011100001111000 %
b11000001000011111011101111101111 &
b11000101101111000000001101110111 (
b11111011010100111011100001111000 )
b11000001000011111011101111101111 *
b11000 +
#37000
b11100011100110100110110001001110 $
b11011101000010011111101001001001 %
b11000000101001000110011010010111 &
b11100011100110100110110001001110 (
b11011101000010011111101001001001 )
b11000000101001000110011010010111 *
b01001 +
#38000
b11111100011111100110110000100000 $
b00000110110110001110001000011010 %
b00000011010101110100111000111010 &
b11111100011111100110110000100000 (
b00000110110110001110001000011010 )
b00000011010101110100111000111010 *
b11010 +
#39000
b11111000100000110011001010110011 $
b10101100011010111101100111000000 %
b10100100111011110000110001110011 &
b11111000100000110011001010110011 (
b10101100011010111101100111000000 )
b10100100111011110000110001110011 *
b00000 +
#40000
b00110100000101111100010000000001 $
b00001111010010111111100000001100 %
b01000011011000111011110000001101 &
b00110100000101111100010000000001 (
b00001111010010111111100000001100 )
b01000011011000111011110000001101 *
b01100 +
#41000
b10111011000001010001100111111000 $
b00000010010000000010001011010011 %
b10111101010001010011110011001011 &
b10111011000001010001100111111000 (
b00000010010000000010001011010011 )
b10111101010001010011110011001011 *
b10011 +
#42000
b00000011011010100100110110010100 $
b00011011011011010011100101000000 %
b00011110110101111000011011010100 &
b00000011011010100100110110010100 (
b00011011011011010011100101000000 )
b00011110110101111000011011010100 *
b00000 +
#43000
b01101001100100010101010010101101 $
b10000100001011011000110011111011 %
b11101101101111101110000110101000 &
b01101001100100010101010010101101 (
b10000100001011011000110011111011 )
b11101101101111101110000110101000 *
b11011 +
#44000
b01110001101111000001111010001001 $
b11101010101100111011110110000011 %
b01011100011011111101110000001100 &
b01110001101111000001111010001001 (
b11101010101100111011110110000011 )
b01011100011011111101110000001100 *
b00011 +
#45000
b00111011111101111001100100010000 $
b11000001111011101101000001100110 %
b11111101111001100110100101110110 &
b00111011111101111001100100010000 (
b11000001111011101101000001100110 )
b11111101111001100110100101110110 *
b00110 +
#46000
b01110010001011000001001100100000 $
b00010010110110101111011010110010 %
b10000101000001110000100111010010 &
b01110010001011000001001100100000 (
b00010010110110101111011010110010 )
b10000101000001110000100111010010 *
b10010 +
#47000
b10011110100111001010101110100111 $
b10010101010110010011000011111101 %
b00110011111101011101110010100100 &
b10011110100111001010101110100111 (
b10010101010110010011000011111101 )
b00110011111101011101110010100100 *
b11101 +
#48000
b00111010101010110001100000000010 $
b00101101001101000100101000110101 %
b01100111110111110110001000110111 &
b00111010101010110001100000000010 (
b00101101001101000100101000110101 )
b01100111110111110110001000110111 *
b10101 +
#49000
b00011110100000111101001001011011 $
b00110111111011010010010111011000 %
b01010110011100001111100000110011 &
b00011110100000111101001001011011 (
b00110111111011010010010111011000 )
b01010110011100001111100000110011 *
b11000 +
#50000
b11111001010001100111110110000100 $
b00100101111000110110101011011010 %
b00011111001010011110100001011110 &
b11111001010001100111110110000100 (
b00100101111000110110101011011010 )
b00011111001010011110100001011110 *
b11010 +
#51000
b11011101010111000010101001010010 $
b00001000101111100000111011111111 %
b11100110000110100011100101010001 &
b11011101010111000010101001010010 (
b00001000101111100000111011111111 )
b11100110000110100011100101010001 *
b11111 +
#52000
b10111001010010011001000011101010 $
b11011101011110101010100111011100 %
b10010110110001000011101011000110 &
b10111001010010011001000011101010 (
b11011101011110101010100111011100 )
b10010110110001000011101011000110 *
b11100 +
#53000
b10111010110001111100010000000111 $
b10001101111110010001010110101000 %
b01001000110000001101100110101111 &
b10111010110001111100010000000111 (
b10001101111110010001010110101000 )
b01001000110000001101100110101111 *
b01000 +
#54000
b01000010010101100010111010110111 $
b10100000111111101000000111111100 %
b11100011010101001011000010110011 &
b01000010010101100010111010110111 (
b10100000111111101000000111111100 )
b11100011010101001011000010110011 *
b11100 +
#55000
b01011001010111011101101111101110 $
b10101000000010101010110111001001 %
b00000001011010001000100110110111 &
b01011001010111011101101111101110 (
b10101000000010101010110111001001 )
b00000001011010001000100110110111 *
b01001 +
#56000
b01010101000111100111101000100111 $
b01101000111000011000100000100010 %
b10111110000000000000001001001001 &
b01010101000111100111101000100111 (
b01101000111000011000100000100010 )
b10111110000000000000001001001001 *
b00010 +
#57000
b10010010011101110011100100101101 $
b11100001101110000011100100110100 %
b01110100001011110111001001100001 &
b10010010011101110011100100101101 (
b11100001101110000011100100110100 )
b01110100001011110111001001100001 *
b10100 +
#58000
b00001100001111000110100010110110 $
b11011100110001001111010011000111 %
b11101001000000010101110101111101 &
b00001100001111000110100010110110 (
b11011100110001001111010011000111 )
b11101001000000010101110101111101 *
b00111 +
#59000
b01011111000111000011001001111101 $
b10001101100111100001010111000100 %
b11101100101110100100100001000001 &
b01011111000111000011001001111101 (
b10001101100111100001010111000100 )
b11101100101110100100100001000001 *
b00100 +
#60000
b10010011010111100111111101100010 $
b10000011100111111100010100011101 %
b00010110111111100100010001111111 &
b10010011010111100111111101100010 (
b10000011100111111100010100011101 )
b00010110111111100100010001111111 *
b11101 +
#61000
b10110011101001100101100101101001 $
b11001101000010000010011000100011 %
b10000000101011100111111110001100 &
b10110011101001100101100101101001 (
b11001101000010000010011000100011 )
b10000000101011100111111110001100 *
b00011 +
#62000
b01001100010000110011001010101100 $
b00110100001110101001000111110100 %
b10000000011111011100010010100000 &
b01001100010000110011001010101100 (
b00110100001110101001000111110100 )
b10000000011111011100010010100000 *
b10100 +
#63000
b10101000110000011001010001111000 $
b11010100101111000110101110101010 %
b01111101011111100000000000100010 &
b10101000110000011001010001111000 (
b11010100101111000110101110101010 )
b01111101011111100000000000100010 *
b01010 +
#64000
b01101001111000101100101010001000 $
b00001011110111101101010101111001 %
b01110101110000011010000000000001 &
b01101001111000101100101010001000 (
b00001011110111101101010101111001 )
b01110101110000011010000000000001 *
b11001 +
#65000
b10011101110111001001010101010100 $
b01000000100111100001010010011101 %
b11011110011110101010100111110001 &
b10011101110111001001010101010100 (
b01000000100111100001010010011101 )
b11011110011110101010100111110001 *
b11101 +
#66000
b00000001000000110000110010110110 $
b10100100111000001101010011100101 %
b10100101111000111110000110011011 &
b00000001000000110000110010110110 (
b10100100111000001101010011100101 )
b10100101111000111110000110011011 *
b00101 +
#67000
b11110010110011000011101000100101 $
b00000110010110001100011101011011 %
b11111001001001010000000110000000 &
b11110010110011000011101000100101 (
b00000110010110001100011101011011 )
b11111001001001010000000110000000 *
b11011 +
#68000
b11010101001101001111011111001011 $
b10000001001110011001111011100001 %
b01010110011011101001011010101100 &
b11010101001101001111011111001011 (
b10000001001110011001111011100001 )
b01010110011011101001011010101100 *
b00001 +
#69000
b01000110100000111100110001110110 $
b11010000010111110001110010011001 %
b00010110111000101110100100001111 &
b01000110100000111100110001110110 (
b11010000010111110001110010011001 )
b00010110111000101110100100001111 *
b11001 +
#70000
b11110100010011101110010011101010 $
b10100010100001101001011010100011 %
b10010110110101010111101110001101 &
b11110100010011101110010011101010 (
b10100010100001101001011010100011 )
b10010110110101010111101110001101 *
b00011 +
#71000
b00000110111110111101011100110100 $
b00011011001110110111111111100011 %
b00100010001101110101011100010111 &
b00000110111110111101011100110100 (
b00011011001110110111111111100011 )
b00100010001101110101011100010111 *
#72000
b10110100001100111010111000001111 $
b11110100100010001011010001011010 %
b10101000101111000110001001101001 &
b10110100001100111010111000001111 (
b11110100100010001011010001011010 )
b10101000101111000110001001101001 *
b11010 +
#73000
b00000010000000000100100100100100 $
b01011111010100010001101000101101 %
b01100001010100010110001101010001 &
b00000010000000000100100100100100 (
b01011111010100010001101000101101 )
b01100001010100010110001101010001 *
b01101 +
#74000
b01001000101000101100001101101110 $
b01110111000110110110110010100010 %
b10111111101111100011000000010000 &
b01001000101000101100001101101110 (
b01110111000110110110110010100010 )
b10111111101111100011000000010000 *
b00010 +
#75000
b01111000000001100100010011110010 $
b00011101101011100111101100011101 %
b10010101101101001100000000001111 &
b01111000000001100100010011110010 (
b00011101101011100111101100011101 )
b10010101101101001100000000001111 *
b11101 +
#76000
b10110011100000011100111111101110 $
b10101000000100101001100101000111 %
b01011011100101000110100100110101 &
b10110011100000011100111111101110 (
b10101000000100101001100101000111 )
b01011011100101000110100100110101 *
b00111 +
#77000
b11011100100000111100111111101011 $
b00011000001000111010010110010011 %
b11110100101001110111010101111110 &
b11011100100000111100111111101011 (
b00011000001000111010010110010011 )
b11110100101001110111010101111110 *
b10011 +
#78000
b01110111010010111100000111111011 $
b00011110010001000100000101001100 %
b10010101100100000000001101000111 &
b01110111010010111100000111111011 (
b00011110010001000100000101001100 )
b10010101100100000000001101000111 *
b01100 +
#79000
b10010111011010110111001000011111 $
b10010100011000010100000100010101 %
b00101011110011001011001100110100 &
b10010111011010110111001000011111 (
b10010100011000010100000100010101 )
b00101011110011001011001100110100 *
b10101 +
#80000
b00010110100001110110000000110111 $
b11110010111111010001011111100001 %
b00001001100001000111100000011000 &
b00010110100001110110000000110111 (
b11110010111111010001011111100001 )
b00001001100001000111100000011000 *
b00001 +
#81000
b00100101110111001000100010001011 $
b11110010010101101010000001000110 %
b00011000001100110010100011010001 &
b00100101110111001000100010001011 (
b11110010010101101010000001000110 )
b00011000001100110010100011010001 *
b00110 +
#82000
b01100001110111011100111010001011 $
b10111101100001111011000111010011 %
b00011111011001011000000001011110 &
b01100001110111011100111010001011 (
b10111101100001111011000111010011 )
b00011111011001011000000001011110 *
b10011 +
#83000
b11101010000100000000101111000101 $
b11110101100100000011001110011001 %
b11011111101000000011111101011110 &
b11101010000100000000101111000101 (
b11110101100100000011001110011001 )
b11011111101000000011111101011110 *
b11001 +
#84000
b01000000101010100100010001011010 $
b00011101100101011000011000011111 %
b01011110001111111100101001111001 &
b01000000101010100100010001011010 (
b00011101100101011000011000011111 )
b01011110001111111100101001111001 *
b11111 +
#85000
b00111110010011010110000101100101 $
b01100001010010011111100110011111 %
b10011111100101110101101100000100 &
b00111110010011010110000101100101 (
b01100001010010011111100110011111 )
b10011111100101110101101100000100 *
#86000
b01101110001001010010100000101110 $
b10100101000111000010001110101100 %
b00010011010000010100101111011010 &
b01101110001001010010100000101110 (
b10100101000111000010001110101100 )
b00010011010000010100101111011010 *
b01100 +
#87000
b00101111001011001101011011111110 $
b10010101011011110011101000000001 %
b11000100100111000001000011111111 &
b00101111001011001101011011111110 (
b10010101011011110011101000000001 )
b11000100100111000001000011111111 *
b00001 +
#88000
b11100001000101111011001100000010 $
b10101000000010001111011011100000 %
b10001001001000001010100111100010 &
b11100001000101111011001100000010 (
b10101000000010001111011011100000 )
b10001001001000001010100111100010 *
b00000 +
#89000
b11010010000111010000100111011100 $
b01101100010011000001011110010100 %
b00111110011010010010000101110000 &
b11010010000111010000100111011100 (
b01101100010011000001011110010100 )
b00111110011010010010000101110000 *
b10100 +
#90000
b00101101010101100100110000101100 $
b11001001011011001110101000000101 %
b11110110110000110011011000110001 &
b00101101010101100100110000101100 (
b11001001011011001110101000000101 )
b11110110110000110011011000110001 *
b00101 +
#91000
b00111111100000011101100011111011 $
b11010110110111001110100101100111 %
b00010110010111101100001001100010 &
b00111111100000011101100011111011 (
b11010110110111001110100101100111 )
b00010110010111101100001001100010 *
b00111 +
#92000
b01000101001111100111110000011001 $
b11011001101111101011011000010111 %
b00011110111111010011001000110000 &
b01000101001111100111110000011001 (
b11011001101111101011011000010111 )
b00011110111111010011001000110000 *
b10111 +
#93000
b00100000001110010100001111111000 $
b10101110001101010010001100101011 %
b11001110011011100110011100100011 &
b00100000001110010100001111111000 (
b10101110001101010010001100101011 )
b11001110011011100110011100100011 *
b01011 +
#94000
b10101010000000000110010101100000 $
b00001011010111110011010011100000 %
b10110101010111111001101001000000 &
b10101010000000000110010101100000 (
b00001011010111110011010011100000 )
b10110101010111111001101001000000 *
b00000 +
#95000
b10010110111111110101011000011000 $
b10110011101010111000101101110000 %
b01001010101010101110000110001000 &
b10010110111111110101011000011000 (
b10110011101010111000101101110000 )
b01001010101010101110000110001000 *
b10000 +
#96000
b00110011100100011010011010010110 $
b01110001000001111011010010010101 %
b10100100100110010101101100101011 &
b00110011100100011010011010010110 (
b01110001000001111011010010010101 )
b10100100100110010101101100101011 *
b10101 +
#97000
b11100100111110000110110011011010 $
b10010010010000100100011011000110 %
b01110111001110101011001110100000 &
b11100100111110000110110011011010 (
b10010010010000100100011011000110 )
b01110111001110101011001110100000 *
b00110 +
#98000
b00010001010100110101011101100010 $
b01111111000000001100100110110011 %
b10010000010101000010000100010101 &
b00010001010100110101011101100010 (
b01111111000000001100100110110011 )
b10010000010101000010000100010101 *
b10011 +
#99000
b00011110001011100110001111101111 $
b10100000000111010011101010000100 %
b10111110010010111001111001110011 &
b00011110001011100110001111101111 (
b10100000000111010011101010000100 )
b10111110010010111001111001110011 *
b00100 +
#100000
b10001001111000011011110011100111 $
b10011011011111111001010100110100 %
b00100101011000010101001000011011 &
b10001001111000011011110011100111 (
b10011011011111111001010100110100 )
b00100101011000010101001000011011 *
b10100 +
#101000
b10101110100111101100101110100001 $
b01100110000000111101100101101001 %
b00010100101000101010010100001010 &
b10101110100111101100101110100001 (
b01100110000000111101100101101001 )
b00010100101000101010010100001010 *
b01001 +
#102000
b01101101010100000111110111011001 $
b01100100000101001010100011101111 %
b11010001011001010010011011001000 &
b01101101010100000111110111011001 (
b01100100000101001010100011101111 )
b11010001011001010010011011001000 *
b01111 +
#103000
b11101010011101110001111011111101 $
b00110000000111000000011000111111 %
b00011010100100110010010100111100 &
b11101010011101110001111011111101 (
b00110000000111000000011000111111 )
b00011010100100110010010100111100 *
b11111 +
#104000
b11011011101110000001111111101110 $
b00101010010110010101001000011111 %
b00000110000100010111001000001101 &
b11011011101110000001111111101110 (
b00101010010110010101001000011111 )
b00000110000100010111001000001101 *
#105000
b00101111100111000010100001111001 $
b00101000000011111100100110101110 %
b01010111101010111111001000100111 &
b00101111100111000010100001111001 (
b00101000000011111100100110101110 )
b01010111101010111111001000100111 *
b01110 +
#106000
b11110111000000000000000011110000 $
b11111011111100000100010110111010 %
b11110010111100000100011010101010 &
b11110111000000000000000011110000 (
b11111011111100000100010110111010 )
b11110010111100000100011010101010 *
b11010 +
#107000
b11011011000110110101101000110011 $
b01001010101101010010111110111011 %
b00100101110100001000100111101110 &
b11011011000110110101101000110011 (
b01001010101101010010111110111011 )
b00100101110100001000100111101110 *
b11011 +
#108000
b00101000010001101010110000101010 $
b10100111101110011100010100011100 %
b11010000000000000111000101000110 &
b00101000010001101010110000101010 (
b10100111101110011100010100011100 )
b11010000000000000111000101000110 *
b11100 +
#109000
b10011000110110000101011011110000 $
b11110011100011000100001000010101 %
b10001100011001001001100100000101 &
b10011000110110000101011011110000 (
b11110011100011000100001000010101 )
b10001100011001001001100100000101 *
b10101 +
#110000
b11111101100010111100111110001100 $
b00000000001101010110100101011100 %
b11111101110000010011100011101000 &
b11111101100010111100111110001100 (
b00000000001101010110100101011100 )
b11111101110000010011100011101000 *
b11100 +
#111000
b10000101111010101010100010000011 $
b11000100011010101110011100100000 %
b01001010010101011000111110100011 &
b10000101111010101010100010000011 (
b11000100011010101110011100100000 )
b01001010010101011000111110100011 *
b00000 +
#112000
b00100100110000101110101110101110 $
b00001110011100111011111000101110 %
b00110011001101101010100111011100 &
b00100100110000101110101110101110 (
b00001110011100111011111000101110 )
b00110011001101101010100111011100 *
b01110 +
#113000
b00001000010111111101110110111100 $
b10001000011011111111010010101101 %
b10010000110011111101001001101001 &
b00001000010111111101110110111100 (
b10001000011011111111010010101101 )
b10010000110011111101001001101001 *
b01101 +
#114000
b01000010110100000100101001100100 $
b00011100111101101110000000000100 %
b01011111110001110010101001101000 &
b01000010110100000100101001100100 (
b00011100111101101110000000000100 )
b01011111110001110010101001101000 *
b00100 +
#115000
b01110111101010001100110010111011 $
b00111100011101110110010000110001 %
b10110100001000000011000011101100 &
b01110111101010001100110010111011 (
b00111100011101110110010000110001 )
b10110100001000000011000011101100 *
b10001 +
#116000
b01100110011000100110100110011101 $
b01101101010110100010001101101001 %
b11010011101111001000110100000110 &
b01100110011000100110100110011101 (
b01101101010110100010001101101001 )
b11010011101111001000110100000110 *
b01001 +
#117000
b00111100011001001110110100100001 $
b00100010010101001111000000111010 %
b01011110101110011101110101011011 &
b00111100011001001110110100100001 (
b00100010010101001111000000111010 )
b01011110101110011101110101011011 *
b11010 +
#118000
b10001100110100010010011110010110 $
b10000001111000110001011110111010 %
b00001110101101000011111101010000 &
b10001100110100010010011110010110 (
b10000001111000110001011110111010 )
b00001110101101000011111101010000 *
#119000
b11100110100111110111100011110000 $
b10110010110010001110001100001010 %
b10011001011010000101101111111010 &
b11100110100111110111100011110000 (
b10110010110010001110001100001010 )
b10011001011010000101101111111010 *
b01010 +
#120000
b01100001100011100001101101101000 $
b11101010000001000001000100111000 %
b01001011100100100010110010100000 &
b01100001100011100001101101101000 (
b11101010000001000001000100111000 )
b01001011100100100010110010100000 *
b11000 +
#121000
b01111100110101110111000101101100 $
b10111011111100011001000111001000 %
b00111000110010010000001100110100 &
b01111100110101110111000101101100 (
b10111011111100011001000111001000 )
b00111000110010010000001100110100 *
b01000 +
#122000
b01011010111000110001000110110010 $
b11111010111011101100000010001100 %
b01010101110100011101001000111110 &
b01011010111000110001000110110010 (
b11111010111011101100000010001100 )
b01010101110100011101001000111110 *
b01100 +
#123000
b01100011111010110110111000100010 $
b01110001001101000010000110001000 %
b11010101000111111000111110101010 &
b01100011111010110110111000100010 (
b01110001001101000010000110001000 )
b11010101000111111000111110101010 *
b01000 +
#124000
b10101101001100010011010111111101 $
b10100100011000000101111001001001 %
b01010001100100011001010001000110 &
b10101101001100010011010111111101 (
b10100100011000000101111001001001 )
b01010001100100011001010001000110 *
b01001 +
#125000
b11011000111110001101111100010100 $
b01010100000001100010010101101010 %
b00101100111111110000010001111110 &
b11011000111110001101111100010100 (
b01010100000001100010010101101010 )
b00101100111111110000010001111110 *
b01010 +
#126000
b10010000001110010111100010000100 $
b01100000101100000011000000101110 %
b11110000111010011010100010110010 &
b10010000001110010111100010000100 (
b01100000101100000011000000101110 )
b11110000111010011010100010110010 *
b01110 +
#127000
b10011111110110011101101010010000 $
b01111110101101010101111101011111 %
b00011110100011110011100111101111 &
b10011111110110011101101010010000 (
b01111110101101010101111101011111 )
b00011110100011110011100111101111 *
b11111 +
#128000
b10110001110001100111000110110111 $
b00010110111110001101011110001011 %
b11001000101111110100100101000010 &
b10110001110001100111000110110111 (
b00010110111110001101011110001011 )
b11001000101111110100100101000010 *
b01011 +
#129000
b10010011111011111101111001001011 $
b00001011001100011110101110011111 %
b10011111001000011100100111101010 &
b10010011111011111101111001001011 (
b00001011001100011110101110011111 )
b10011111001000011100100111101010 *
b11111 +
#130000
b11110001011100011100110110000001 $
b01001010001010101010010010000100 %
b00111011100111000111001000000101 &
b11110001011100011100110110000001 (
b01001010001010101010010010000100 )
b00111011100111000111001000000101 *
b00100 +
#131000
b01100110011010110111110011101010 $
b01001001010001001110001010111111 %
b10101111101100000101111110101001 &
b01100110011010110111110011101010 (
b01001001010001001110001010111111 )
b10101111101100000101111110101001 *
b11111 +
#132000
b11011011100011000100010011100101 $
b10011111101100010011100101011001 %
b01111011001111010111111000111110 &
b11011011100011000100010011100101 (
b10011111101100010011100101011001 )
b01111011001111010111111000111110 *
b11001 +
#133000
b00110100100111001110100101011001 $
b10000111000011111000101000111010 %
b10111011101011000111001110010011 &
b00110100100111001110100101011001 (
b10000111000011111000101000111010 )
b10111011101011000111001110010011 *
b11010 +
#134000
b10000100001100110001011100011010 $
b00111110011010000010000110110011 %
b11000010100110110011100011001101 &
b10000100001100110001011100011010 (
b00111110011010000010000110110011 )
b11000010100110110011100011001101 *
b10011 +
#135000
b00101110101001100100010001111010 $
b01111001111110010111000110011011 %
b10101000100111111011011000010101 &
b00101110101001100100010001111010 (
b01111001111110010111000110011011 )
b10101000100111111011011000010101 *
b11011 +
#136000
b11110011110001111001011110111011 $
b11101000100111111011010111010110 %
b11011100011001110100110110010001 &
b11110011110001111001011110111011 (
b11101000100111111011010111010110 )
b11011100011001110100110110010001 *
b10110 +
#137000
b11000011001000001100101111101010 $
b01001110001110111101110011000000 %
b00010001010111001010100010101010 &
b11000011001000001100101111101010 (
b01001110001110111101110011000000 )
b00010001010111001010100010101010 *
b00000 +
#138000
b00001001110111111010111001100110 $
b01110001111110100000011011110100 %
b01111011110110011011010101011010 &
b00001001110111111010111001100110 (
b01110001111110100000011011110100 )
b01111011110110011011010101011010 *
b10100 +
#139000
b00001010000001000000000110010000 $
b11010100110100011100001101000100 %
b11011110110101011100010011010100 &
b00001010000001000000000110010000 (
b11010100110100011100001101000100 )
b11011110110101011100010011010100 *
b00100 +
#140000
b11010011101100100000001000000110 $
b11000100001011111111001100011010 %
b10010111111000011111010100100000 &
b11010011101100100000001000000110 (
b11000100001011111111001100011010 )
b10010111111000011111010100100000 *
b11010 +
#141000
b01111000100001110100100100110101 $
b00100000000010011111100110111001 %
b10011000100100010100001011101110 &
b01111000100001110100100100110101 (
b00100000000010011111100110111001 )
b10011000100100010100001011101110 *
b11001 +
#142000
b00111000110011010001100101000110 $
b10000111011000100100110110111001 %
b11000000001011110110011011111111 &
b00111000110011010001100101000110 (
b10000111011000100100110110111001 )
b11000000001011110110011011111111 *
