design/register_file.sv
module register_file #(
    parameter DATA_WIDTH = 32,
              ADDR_WIDTH = 5
) (
    input logic clk,
    input logic write_enable,
    input logic [ADDR_WIDTH - 1:0] rs1,
    input logic [ADDR_WIDTH - 1:0] rs2,
    input logic [ADDR_WIDTH - 1:0] rd,
    input logic [DATA_WIDTH - 1:0] reg_data_in,
    input logic reset,


    output logic [DATA_WIDTH -1:0] reg_data_out_1,
    output logic [DATA_WIDTH -1:0] reg_data_out_2
    
);

logic [DATA_WIDTH - 1:0] registers [0: 2** ADDR_WIDTH -1];

always_ff @( posedge clk ) begin
    if (reset == 1'b0) begin
        for (int i = 0; i < 2 ** ADDR_WIDTH; i++) begin
            registers[i] <= 32'd0;
        end
    end
    else if (write_enable == 1'b1)begin
    registers[rd] <= reg_data_in;
    end

end

assign reg_data_out_1 = registers[rs1];
assign reg_data_out_2 = registers[rs2];

endmodule

tb/register_file/dump.vcd
$version Generated by VerilatedVcd $end
$timescale 1ps $end
 $scope module $rootio $end
  $var wire 1 # clk $end
  $var wire 1 $ write_enable $end
  $var wire 5 % rs1 [4:0] $end
  $var wire 5 & rs2 [4:0] $end
  $var wire 5 ' rd [4:0] $end
  $var wire 32 ( reg_data_in [31:0] $end
  $var wire 1 ) reset $end
  $var wire 32 * reg_data_out_1 [31:0] $end
  $var wire 32 + reg_data_out_2 [31:0] $end
 $upscope $end
 $scope module register_file $end
  $var wire 32 V DATA_WIDTH [31:0] $end
  $var wire 32 W ADDR_WIDTH [31:0] $end
  $var wire 1 , clk $end
  $var wire 1 - write_enable $end
  $var wire 5 . rs1 [4:0] $end
  $var wire 5 / rs2 [4:0] $end
  $var wire 5 0 rd [4:0] $end
  $var wire 32 1 reg_data_in [31:0] $end
  $var wire 1 2 reset $end
  $var wire 32 3 reg_data_out_1 [31:0] $end
  $var wire 32 4 reg_data_out_2 [31:0] $end
  $var wire 32 5 registers[0] [31:0] $end
  $var wire 32 6 registers[1] [31:0] $end
  $var wire 32 7 registers[2] [31:0] $end
  $var wire 32 8 registers[3] [31:0] $end
  $var wire 32 9 registers[4] [31:0] $end
  $var wire 32 : registers[5] [31:0] $end
  $var wire 32 ; registers[6] [31:0] $end
  $var wire 32 < registers[7] [31:0] $end
  $var wire 32 = registers[8] [31:0] $end
  $var wire 32 > registers[9] [31:0] $end
  $var wire 32 ? registers[10] [31:0] $end
  $var wire 32 @ registers[11] [31:0] $end
  $var wire 32 A registers[12] [31:0] $end
  $var wire 32 B registers[13] [31:0] $end
  $var wire 32 C registers[14] [31:0] $end
  $var wire 32 D registers[15] [31:0] $end
  $var wire 32 E registers[16] [31:0] $end
  $var wire 32 F registers[17] [31:0] $end
  $var wire 32 G registers[18] [31:0] $end
  $var wire 32 H registers[19] [31:0] $end
  $var wire 32 I registers[20] [31:0] $end
  $var wire 32 J registers[21] [31:0] $end
  $var wire 32 K registers[22] [31:0] $end
  $var wire 32 L registers[23] [31:0] $end
  $var wire 32 M registers[24] [31:0] $end
  $var wire 32 N registers[25] [31:0] $end
  $var wire 32 O registers[26] [31:0] $end
  $var wire 32 P registers[27] [31:0] $end
  $var wire 32 Q registers[28] [31:0] $end
  $var wire 32 R registers[29] [31:0] $end
  $var wire 32 S registers[30] [31:0] $end
  $var wire 32 T registers[31] [31:0] $end
  $scope module unnamedblk1 $end
   $var wire 32 U i [31:0] $end
  $upscope $end
 $upscope $end
$enddefinitions $end


#0
1#
0$
b00000 %
b00000 &
b00000 '
b00000000000000000000000000000000 (
0)
b00000000000000000000000000000000 *
b00000000000000000000000000000000 +
1,
0-
b00000 .
b00000 /
b00000 0
b00000000000000000000000000000000 1
02
b00000000000000000000000000000000 3
b00000000000000000000000000000000 4
b00000000000000000000000000000000 5
b00000000000000000000000000000000 6
b00000000000000000000000000000000 7
b00000000000000000000000000000000 8
b00000000000000000000000000000000 9
b00000000000000000000000000000000 :
b00000000000000000000000000000000 ;
b00000000000000000000000000000000 <
b00000000000000000000000000000000 =
b00000000000000000000000000000000 >
b00000000000000000000000000000000 ?
b00000000000000000000000000000000 @
b00000000000000000000000000000000 A
b00000000000000000000000000000000 B
b00000000000000000000000000000000 C
b00000000000000000000000000000000 D
b00000000000000000000000000000000 E
b00000000000000000000000000000000 F
b00000000000000000000000000000000 G
b00000000000000000000000000000000 H
b00000000000000000000000000000000 I
b00000000000000000000000000000000 J
b00000000000000000000000000000000 K
b00000000000000000000000000000000 L
b00000000000000000000000000000000 M
b00000000000000000000000000000000 N
b00000000000000000000000000000000 O
b00000000000000000000000000000000 P
b00000000000000000000000000000000 Q
b00000000000000000000000000000000 R
b00000000000000000000000000000000 S
b00000000000000000000000000000000 T
b00000000000000000000000000100000 U
b00000000000000000000000000100000 V
b00000000000000000000000000000101 W
#5000
0#
0,
#10000
1#
1)
1,
12
#15000
0#
0,
#20000
1#
1,
#21000
b00110 %
b00110 &
b00110 .
b00110 /
#22000
1$
b10011 '
b11000111100010000000110000011011 (
1-
b10011 0
b11000111100010000000110000011011 1
#25000
0#
0,
#30000
1#
0$
1,
0-
b11000111100010000000110000011011 H
#31000
#32000
b10011 %
b11110 &
b11000111100010000000110000011011 *
b10011 .
b11110 /
b11000111100010000000110000011011 3
#33000
1$
b11111 '
b11010001100101101100001001010110 (
1-
b11111 0
b11010001100101101100001001010110 1
#35000
0#
0,
#40000
1#
0$
1,
0-
b11010001100101101100001001010110 T
#41000
#42000
b01100 %
b10001 &
b00000000000000000000000000000000 *
b01100 .
b10001 /
b00000000000000000000000000000000 3
#43000
1$
b10110 '
b10100010110110000010010001001110 (
1-
b10110 0
b10100010110110000010010001001110 1
#45000
0#
0,
#50000
1#
0$
1,
0-
b10100010110110000010010001001110 K
#51000
#52000
b11001 %
b10010 &
b11001 .
b10010 /
#53000
1$
b00100 '
b00111110000010001000111001000110 (
1-
b00100 0
b00111110000010001000111001000110 1
#55000
0#
0,
#60000
1#
0$
1,
0-
b00111110000010001000111001000110 9
#61000
#62000
b00011 %
b00111 &
b00011 .
b00111 /
#63000
1$
b10110 '
b10000111001000101111101001100100 (
1-
b10110 0
b10000111001000101111101001100100 1
#65000
0#
0,
#70000
1#
0$
1,
0-
b10000111001000101111101001100100 K
#71000
#72000
b11011 %
b10110 &
b10000111001000101111101001100100 +
b11011 .
b10110 /
b10000111001000101111101001100100 4
#73000
1$
b00001 '
b11101010000111011001010110100100 (
1-
b00001 0
b11101010000111011001010110100100 1
#75000
0#
0,
#80000
1#
0$
1,
0-
b11101010000111011001010110100100 6
#81000
#82000
b11000 %
b10000 &
b00000000000000000000000000000000 +
b11000 .
b10000 /
b00000000000000000000000000000000 4
#83000
1$
b10101 '
b10101000101100110001101001101110 (
1-
b10101 0
b10101000101100110001101001101110 1
#85000
0#
0,
#90000
1#
0$
1,
0-
b10101000101100110001101001101110 J
#91000
#92000
b00010 %
b10101 &
b10101000101100110001101001101110 +
b00010 .
b10101 /
b10101000101100110001101001101110 4
#93000
1$
b10111 '
b00101000110000100010100111100110 (
1-
b10111 0
b00101000110000100010100111100110 1
#95000
0#
0,
#100000
1#
0$
1,
0-
b00101000110000100010100111100110 L
#101000
#102000
b10111 %
b01011 &
b00101000110000100010100111100110 *
b00000000000000000000000000000000 +
b10111 .
b01011 /
b00101000110000100010100111100110 3
b00000000000000000000000000000000 4
#103000
1$
b00010 '
b00101110000000000011010100100110 (
1-
b00010 0
b00101110000000000011010100100110 1
#105000
0#
0,
#110000
1#
0$
1,
0-
b00101110000000000011010100100110 7
#111000
#112000
b11001 %
b00001 &
b00000000000000000000000000000000 *
b11101010000111011001010110100100 +
b11001 .
b00001 /
b00000000000000000000000000000000 3
b11101010000111011001010110100100 4
#113000
1$
b00001 '
b10010000011011001000011011111011 (
1-
b00001 0
b10010000011011001000011011111011 1
#115000
0#
0,
#120000
1#
0$
b10010000011011001000011011111011 +
1,
0-
b10010000011011001000011011111011 4
b10010000011011001000011011111011 6
#121000
#122000
b11100 %
b11001 &
b00000000000000000000000000000000 +
b11100 .
b11001 /
b00000000000000000000000000000000 4
#123000
1$
b11110 '
b01101011010010001111000111011011 (
1-
b11110 0
b01101011010010001111000111011011 1
#125000
0#
0,
#130000
1#
0$
1,
0-
b01101011010010001111000111011011 S
#131000
#132000
b01100 %
b11000 &
b01100 .
b11000 /
#133000
1$
b10011 '
b01111100001100110100000111101101 (
1-
b10011 0
b01111100001100110100000111101101 1
#135000
0#
0,
#140000
1#
0$
1,
0-
b01111100001100110100000111101101 H
#141000
#142000
b01111 %
b10111 &
b00101000110000100010100111100110 +
b01111 .
b10111 /
b00101000110000100010100111100110 4
#143000
1$
b01000 '
b00011010111000001101101001001011 (
1-
b01000 0
b00011010111000001101101001001011 1
#145000
0#
0,
#150000
1#
0$
1,
0-
b00011010111000001101101001001011 =
#151000
#152000
b11101 %
b01011 &
b00000000000000000000000000000000 +
b11101 .
b01011 /
b00000000000000000000000000000000 4
#153000
1$
b01100 '
b10000100100111011110000100110000 (
1-
b01100 0
b10000100100111011110000100110000 1
#155000
0#
0,
#160000
1#
0$
1,
0-
b10000100100111011110000100110000 A
#161000
#162000
b10001 %
b01000 &
b00011010111000001101101001001011 +
b10001 .
b01000 /
b00011010111000001101101001001011 4
#163000
1$
b10110 '
b00000010000111111011000000010001 (
1-
b10110 0
b00000010000111111011000000010001 1
#165000
0#
0,
#170000
1#
0$
1,
0-
b00000010000111111011000000010001 K
#171000
#172000
b11001 %
b11111 &
b11010001100101101100001001010110 +
b11001 .
b11111 /
b11010001100101101100001001010110 4
#173000
1$
b11110 '
b11110001000110100100000110100101 (
1-
b11110 0
b11110001000110100100000110100101 1
#175000
0#
0,
#180000
1#
0$
1,
0-
b11110001000110100100000110100101 S
#181000
#182000
b00011 %
b11110 &
b11110001000110100100000110100101 +
b00011 .
b11110 /
b11110001000110100100000110100101 4
#183000
1$
b01000 '
b10100010110010110001111001110100 (
1-
b01000 0
b10100010110010110001111001110100 1
#185000
0#
0,
#190000
1#
0$
1,
0-
b10100010110010110001111001110100 =
#191000
#192000
b01100 %
b10110 &
b10000100100111011110000100110000 *
b00000010000111111011000000010001 +
b01100 .
b10110 /
b10000100100111011110000100110000 3
b00000010000111111011000000010001 4
#193000
1$
b00111 '
b10100001000010000010101011000110 (
1-
b00111 0
b10100001000010000010101011000110 1
#195000
0#
0,
#200000
1#
0$
1,
0-
b10100001000010000010101011000110 <
#201000
#202000
b00110 %
b11100 &
b00000000000000000000000000000000 *
b00000000000000000000000000000000 +
b00110 .
b11100 /
b00000000000000000000000000000000 3
b00000000000000000000000000000000 4
#203000
1$
b01110 '
b10100000110001000011101101000000 (
1-
b01110 0
b10100000110001000011101101000000 1
#205000
0#
0,
#210000
1#
0$
1,
0-
b10100000110001000011101101000000 C
#211000
#212000
b11010 &
b11010 /
#213000
1$
b11101 '
b10011010011001010110110100011001 (
1-
b11101 0
b10011010011001010110110100011001 1
#215000
0#
0,
#220000
1#
0$
1,
0-
b10011010011001010110110100011001 R
#221000
#222000
b01101 %
b01100 &
b10000100100111011110000100110000 +
b01101 .
b01100 /
b10000100100111011110000100110000 4
#223000
1$
b01100 '
b01000111100111110011100000001001 (
1-
b01100 0
b01000111100111110011100000001001 1
#225000
0#
0,
#230000
1#
0$
b01000111100111110011100000001001 +
1,
0-
b01000111100111110011100000001001 4
b01000111100111110011100000001001 A
#231000
#232000
b00100 %
b01011 &
b00111110000010001000111001000110 *
b00000000000000000000000000000000 +
b00100 .
b01011 /
b00111110000010001000111001000110 3
b00000000000000000000000000000000 4
#233000
1$
b01110 '
b11000011001001011100110010010000 (
1-
b01110 0
b11000011001001011100110010010000 1
#235000
0#
0,
#240000
1#
0$
1,
0-
b11000011001001011100110010010000 C
#241000
#242000
b00110 %
b00101 &
b00000000000000000000000000000000 *
b00110 .
b00101 /
b00000000000000000000000000000000 3
#243000
1$
b11011 '
b10101010000001101011100101011011 (
1-
b11011 0
b10101010000001101011100101011011 1
#245000
0#
0,
#250000
1#
0$
1,
0-
b10101010000001101011100101011011 P
#251000
#252000
b11011 %
b11001 &
b10101010000001101011100101011011 *
b11011 .
b11001 /
b10101010000001101011100101011011 3
#253000
1$
b10010 '
b00100101001111000011100100001111 (
1-
b10010 0
b00100101001111000011100100001111 1
#255000
0#
0,
#260000
1#
0$
1,
0-
b00100101001111000011100100001111 G
#261000
#262000
b10111 %
b11000 &
b00101000110000100010100111100110 *
b10111 .
b11000 /
b00101000110000100010100111100110 3
#263000
1$
b01101 '
b01011011011110011111010101101101 (
1-
b01101 0
b01011011011110011111010101101101 1
#265000
0#
0,
#270000
1#
0$
1,
0-
b01011011011110011111010101101101 B
#271000
#272000
b01010 %
b10110 &
b00000000000000000000000000000000 *
b00000010000111111011000000010001 +
b01010 .
b10110 /
b00000000000000000000000000000000 3
b00000010000111111011000000010001 4
#273000
1$
b11101 '
b01001100000110010001110101111011 (
1-
b11101 0
b01001100000110010001110101111011 1
#275000
0#
0,
#280000
1#
0$
1,
0-
b01001100000110010001110101111011 R
#281000
#282000
b11100 %
b11101 &
b01001100000110010001110101111011 +
b11100 .
b11101 /
b01001100000110010001110101111011 4
#283000
1$
b01101 '
b01011101000101110101110101011110 (
1-
b01101 0
b01011101000101110101110101011110 1
#285000
0#
0,
#290000
1#
0$
1,
0-
b01011101000101110101110101011110 B
#291000
#292000
b11000 %
b11011 &
b10101010000001101011100101011011 +
b11000 .
b11011 /
b10101010000001101011100101011011 4
#293000
1$
b00011 '
b10101101011011110010100000000011 (
1-
b00011 0
b10101101011011110010100000000011 1
#295000
0#
0,
#300000
1#
0$
1,
0-
b10101101011011110010100000000011 8
#301000
#302000
b01101 %
b11100 &
b01011101000101110101110101011110 *
b00000000000000000000000000000000 +
b01101 .
b11100 /
b01011101000101110101110101011110 3
b00000000000000000000000000000000 4
#303000
1$
b11110 '
b00101000000111101010111011010101 (
1-
b11110 0
b00101000000111101010111011010101 1
#305000
0#
0,
#310000
1#
0$
1,
0-
b00101000000111101010111011010101 S
#311000
#312000
b10111 %
b01101 &
b00101000110000100010100111100110 *
b01011101000101110101110101011110 +
b10111 .
b01101 /
b00101000110000100010100111100110 3
b01011101000101110101110101011110 4
#313000
1$
b11011 '
b01110111000101001010001000101100 (
1-
b11011 0
b01110111000101001010001000101100 1
#315000
0#
0,
#320000
1#
0$
1,
0-
b01110111000101001010001000101100 P
#321000
#322000
b11110 %
b01010 &
b00101000000111101010111011010101 *
b00000000000000000000000000000000 +
b11110 .
b01010 /
b00101000000111101010111011010101 3
b00000000000000000000000000000000 4
#323000
1$
b00001 '
b01110001111110100101001100111101 (
1-
b00001 0
b01110001111110100101001100111101 1
#325000
0#
0,
#330000
1#
0$
1,
0-
b01110001111110100101001100111101 6
#331000
#332000
b01100 %
b00010 &
b01000111100111110011100000001001 *
b00101110000000000011010100100110 +
b01100 .
b00010 /
b01000111100111110011100000001001 3
b00101110000000000011010100100110 4
#333000
1$
b00010 '
b10100000010000101111001010000100 (
1-
b00010 0
b10100000010000101111001010000100 1
#335000
0#
0,
#340000
1#
0$
b10100000010000101111001010000100 +
1,
0-
b10100000010000101111001010000100 4
b10100000010000101111001010000100 7
#341000
#342000
b10000 %
b11000 &
b00000000000000000000000000000000 *
b00000000000000000000000000000000 +
b10000 .
b11000 /
b00000000000000000000000000000000 3
b00000000000000000000000000000000 4
#343000
1$
b01111 '
b01110001110110111000001100111100 (
1-
b01111 0
b01110001110110111000001100111100 1
#345000
0#
0,
#350000
1#
0$
1,
0-
b01110001110110111000001100111100 D
#351000
#352000
b11010 %
b01110 &
b11000011001001011100110010010000 +
b11010 .
b01110 /
b11000011001001011100110010010000 4
#353000
1$
b10110 '
b01000011101011010001100011111010 (
1-
b10110 0
b01000011101011010001100011111010 1
#355000
0#
0,
#360000
1#
0$
1,
0-
b01000011101011010001100011111010 K
#361000
#362000
b01000 %
b10101 &
b10100010110010110001111001110100 *
b10101000101100110001101001101110 +
b01000 .
b10101 /
b10100010110010110001111001110100 3
b10101000101100110001101001101110 4
#363000
1$
b11010 '
b00001001000110101100001001010100 (
1-
b11010 0
b00001001000110101100001001010100 1
#365000
0#
0,
#370000
1#
0$
1,
0-
b00001001000110101100001001010100 O
#371000
#372000
b01101 %
b00101 &
b01011101000101110101110101011110 *
b00000000000000000000000000000000 +
b01101 .
b00101 /
b01011101000101110101110101011110 3
b00000000000000000000000000000000 4
#373000
1$
b01001 '
b10010100110001010101100110110101 (
1-
b01001 0
b10010100110001010101100110110101 1
#375000
0#
0,
#380000
1#
0$
1,
0-
b10010100110001010101100110110101 >
#381000
#382000
b00101 %
b10011 &
b00000000000000000000000000000000 *
b01111100001100110100000111101101 +
b00101 .
b10011 /
b00000000000000000000000000000000 3
b01111100001100110100000111101101 4
#383000
1$
b11111 '
b10011010110101011001010010101110 (
1-
b11111 0
b10011010110101011001010010101110 1
#385000
0#
0,
#390000
1#
0$
1,
0-
b10011010110101011001010010101110 T
#391000
#392000
b01110 %
b11010 &
b11000011001001011100110010010000 *
b00001001000110101100001001010100 +
b01110 .
b11010 /
b11000011001001011100110010010000 3
b00001001000110101100001001010100 4
#393000
1$
b10101 '
b10111010000011100000111100010100 (
1-
b10101 0
b10111010000011100000111100010100 1
#395000
0#
0,
#400000
1#
0$
1,
0-
b10111010000011100000111100010100 J
#401000
#402000
b01101 %
b10011 &
b01011101000101110101110101011110 *
b01111100001100110100000111101101 +
b01101 .
b10011 /
b01011101000101110101110101011110 3
b01111100001100110100000111101101 4
#403000
1$
b11101 '
b10100101011100011111100001101010 (
1-
b11101 0
b10100101011100011111100001101010 1
#405000
0#
0,
#410000
1#
0$
1,
0-
b10100101011100011111100001101010 R
#411000
#412000
b01110 %
b11001 &
b11000011001001011100110010010000 *
b00000000000000000000000000000000 +
b01110 .
b11001 /
b11000011001001011100110010010000 3
b00000000000000000000000000000000 4
#413000
1$
b00001 '
b00110000110011000101001001100111 (
1-
b00001 0
b00110000110011000101001001100111 1
#415000
0#
0,
#420000
1#
0$
1,
0-
b00110000110011000101001001100111 6
#421000
#422000
b10010 %
b11000 &
b00100101001111000011100100001111 *
b10010 .
b11000 /
b00100101001111000011100100001111 3
#423000
1$
b10010 '
b00010000100100101111111101110111 (
1-
b10010 0
b00010000100100101111111101110111 1
#425000
0#
0,
#430000
1#
0$
b00010000100100101111111101110111 *
1,
0-
b00010000100100101111111101110111 3
b00010000100100101111111101110111 G
#431000
#432000
b10001 %
b11101 &
b00000000000000000000000000000000 *
b10100101011100011111100001101010 +
b10001 .
b11101 /
b00000000000000000000000000000000 3
b10100101011100011111100001101010 4
#433000
1$
b11100 '
b00010110011010010111000110110111 (
1-
b11100 0
b00010110011010010111000110110111 1
#435000
0#
0,
#440000
1#
0$
1,
0-
b00010110011010010111000110110111 Q
#441000
#442000
b00001 %
b00100 &
b00110000110011000101001001100111 *
b00111110000010001000111001000110 +
b00001 .
b00100 /
b00110000110011000101001001100111 3
b00111110000010001000111001000110 4
#443000
1$
b00101 '
b11110100110001111101110101011011 (
1-
b00101 0
b11110100110001111101110101011011 1
#445000
0#
0,
#450000
1#
0$
1,
0-
b11110100110001111101110101011011 :
#451000
#452000
b00111 %
b00111 &
b10100001000010000010101011000110 *
b10100001000010000010101011000110 +
b00111 .
b00111 /
b10100001000010000010101011000110 3
b10100001000010000010101011000110 4
#453000
1$
b01100 '
b11001110001001100100101011101111 (
1-
b01100 0
b11001110001001100100101011101111 1
#455000
0#
0,
#460000
1#
0$
1,
0-
b11001110001001100100101011101111 A
#461000
#462000
b01010 %
b11100 &
b00000000000000000000000000000000 *
b00010110011010010111000110110111 +
b01010 .
b11100 /
b00000000000000000000000000000000 3
b00010110011010010111000110110111 4
#463000
1$
b01010 '
b00110010001100100111110111111101 (
1-
b01010 0
b00110010001100100111110111111101 1
#465000
0#
0,
#470000
1#
0$
b00110010001100100111110111111101 *
1,
0-
b00110010001100100111110111111101 3
b00110010001100100111110111111101 ?
#471000
#472000
b11010 %
b00100 &
b00001001000110101100001001010100 *
b00111110000010001000111001000110 +
b11010 .
b00100 /
b00001001000110101100001001010100 3
b00111110000010001000111001000110 4
#473000
1$
b01100 '
b11000110111001010011100101011000 (
1-
b01100 0
b11000110111001010011100101011000 1
#475000
0#
0,
#480000
1#
0$
1,
0-
b11000110111001010011100101011000 A
#481000
#482000
b10110 %
b11011 &
b01000011101011010001100011111010 *
b01110111000101001010001000101100 +
b10110 .
b11011 /
b01000011101011010001100011111010 3
b01110111000101001010001000101100 4
#483000
1$
b10101 '
b11010100110010100110101101010100 (
1-
b10101 0
b11010100110010100110101101010100 1
#485000
0#
0,
#490000
1#
0$
1,
0-
b11010100110010100110101101010100 J
#491000
#492000
b10000 %
b01010 &
b00000000000000000000000000000000 *
b00110010001100100111110111111101 +
b10000 .
b01010 /
b00000000000000000000000000000000 3
b00110010001100100111110111111101 4
#493000
1$
b00001 '
b00110010011101011110001010001010 (
1-
b00001 0
b00110010011101011110001010001010 1
#495000
0#
0,
#500000
1#
0$
1,
0-
b00110010011101011110001010001010 6
#501000
#502000
b01110 %
b10110 &
b11000011001001011100110010010000 *
b01000011101011010001100011111010 +
b01110 .
b10110 /
b11000011001001011100110010010000 3
b01000011101011010001100011111010 4
#503000
1$
b00100 '
b11101111111100110000101101001010 (
1-
b00100 0
b11101111111100110000101101001010 1
#505000
0#
0,
#510000
1#
0$
1,
0-
b11101111111100110000101101001010 9
#511000
#512000
b10111 %
b10011 &
b00101000110000100010100111100110 *
b01111100001100110100000111101101 +
b10111 .
b10011 /
b00101000110000100010100111100110 3
b01111100001100110100000111101101 4
#513000
1$
b00001 '
b10110100000100010110001011110101 (
1-
b00001 0
b10110100000100010110001011110101 1
#515000
0#
0,
#520000
1#
0$
1,
0-
b10110100000100010110001011110101 6
#521000
#522000
b00010 %
b11110 &
b10100000010000101111001010000100 *
b00101000000111101010111011010101 +
b00010 .
b11110 /
b10100000010000101111001010000100 3
b00101000000111101010111011010101 4
#523000
1$
b11001 '
b11011000001100000000101001111100 (
1-
b11001 0
b11011000001100000000101001111100 1
#525000
0#
0,
#530000
1#
0$
1,
0-
b11011000001100000000101001111100 N
#531000
#532000
b01111 %
b11111 &
b01110001110110111000001100111100 *
b10011010110101011001010010101110 +
b01111 .
b11111 /
b01110001110110111000001100111100 3
b10011010110101011001010010101110 4
#533000
1$
b01101 '
b11011000100110111001101010111110 (
1-
b01101 0
b11011000100110111001101010111110 1
#535000
0#
0,
#540000
1#
0$
1,
0-
b11011000100110111001101010111110 B
#541000
#542000
b10011 %
b01000 &
b01111100001100110100000111101101 *
b10100010110010110001111001110100 +
b10011 .
b01000 /
b01111100001100110100000111101101 3
b10100010110010110001111001110100 4
#543000
1$
b11001 '
b10001001110101011010001110001100 (
1-
b11001 0
b10001001110101011010001110001100 1
#545000
0#
0,
#550000
1#
0$
1,
0-
b10001001110101011010001110001100 N
#551000
#552000
b00010 %
b11000 &
b10100000010000101111001010000100 *
b00000000000000000000000000000000 +
b00010 .
b11000 /
b10100000010000101111001010000100 3
b00000000000000000000000000000000 4
#553000
1$
b00001 '
b00111101111110110101101010000000 (
1-
b00001 0
b00111101111110110101101010000000 1
#555000
0#
0,
#560000
1#
0$
1,
0-
b00111101111110110101101010000000 6
#561000
#562000
b11111 %
b01011 &
b10011010110101011001010010101110 *
b11111 .
b01011 /
b10011010110101011001010010101110 3
#563000
1$
b11010 '
b11001111000110110111110000001101 (
1-
b11010 0
b11001111000110110111110000001101 1
#565000
0#
0,
#570000
1#
0$
1,
0-
b11001111000110110111110000001101 O
#571000
#572000
b10010 %
b01100 &
b00010000100100101111111101110111 *
b11000110111001010011100101011000 +
b10010 .
b01100 /
b00010000100100101111111101110111 3
b11000110111001010011100101011000 4
#573000
1$
b11000 '
b01000100100101110110111111100010 (
1-
b11000 0
b01000100100101110110111111100010 1
#575000
0#
0,
#580000
1#
0$
1,
0-
b01000100100101110110111111100010 M
#581000
#582000
b11011 %
b01101 &
b01110111000101001010001000101100 *
b11011000100110111001101010111110 +
b11011 .
b01101 /
b01110111000101001010001000101100 3
b11011000100110111001101010111110 4
#583000
1$
b01001 '
b00110111000110010011110011111110 (
1-
b01001 0
b00110111000110010011110011111110 1
#585000
0#
0,
#590000
1#
0$
1,
0-
b00110111000110010011110011111110 >
#591000
#592000
b10010 %
b10001 &
b00010000100100101111111101110111 *
b00000000000000000000000000000000 +
b10010 .
b10001 /
b00010000100100101111111101110111 3
b00000000000000000000000000000000 4
#593000
1$
b11010 '
b00010001001100110000111110110010 (
1-
b11010 0
b00010001001100110000111110110010 1
#595000
0#
0,
#600000
1#
0$
1,
0-
b00010001001100110000111110110010 O
#601000
#602000
b00101 %
b11110100110001111101110101011011 *
b00101 .
b11110100110001111101110101011011 3
#603000
1$
b11100 '
b01001100100101111011001011101001 (
1-
b11100 0
b01001100100101111011001011101001 1
#605000
0#
0,
#610000
1#
0$
1,
0-
b01001100100101111011001011101001 Q
#611000
#612000
b00100 %
b11000 &
b11101111111100110000101101001010 *
b01000100100101110110111111100010 +
b00100 .
b11000 /
b11101111111100110000101101001010 3
b01000100100101110110111111100010 4
#613000
1$
b10101 '
b10010101000111000000011101001100 (
1-
b10101 0
b10010101000111000000011101001100 1
#615000
0#
0,
#620000
1#
0$
1,
0-
b10010101000111000000011101001100 J
#621000
#622000
b11110 %
b11100 &
b00101000000111101010111011010101 *
b01001100100101111011001011101001 +
b11110 .
b11100 /
b00101000000111101010111011010101 3
b01001100100101111011001011101001 4
#623000
1$
b10001 '
b01011110111110101100011111001110 (
1-
b10001 0
b01011110111110101100011111001110 1
#625000
0#
0,
#630000
1#
0$
1,
0-
b01011110111110101100011111001110 F
#631000
#632000
b00001 %
b10110 &
b00111101111110110101101010000000 *
b01000011101011010001100011111010 +
b00001 .
b10110 /
b00111101111110110101101010000000 3
b01000011101011010001100011111010 4
#633000
1$
b10101 '
b11010010111000001010000100100011 (
1-
b10101 0
b11010010111000001010000100100011 1
#635000
0#
0,
#640000
1#
0$
1,
0-
b11010010111000001010000100100011 J
#641000
#642000
b11010 %
b00101 &
b00010001001100110000111110110010 *
b11110100110001111101110101011011 +
b11010 .
b00101 /
b00010001001100110000111110110010 3
b11110100110001111101110101011011 4
#643000
1$
b00100 '
b10010101100110111100101101111000 (
1-
b00100 0
b10010101100110111100101101111000 1
#645000
0#
0,
#650000
1#
0$
1,
0-
b10010101100110111100101101111000 9
#651000
#652000
b10011 %
b10000 &
b01111100001100110100000111101101 *
b00000000000000000000000000000000 +
b10011 .
b10000 /
b01111100001100110100000111101101 3
b00000000000000000000000000000000 4
#653000
1$
b11100 '
b10110111000111111000001100011111 (
1-
b11100 0
b10110111000111111000001100011111 1
#655000
0#
0,
#660000
1#
0$
1,
0-
b10110111000111111000001100011111 Q
#661000
#662000
b10001 %
b01000 &
b01011110111110101100011111001110 *
b10100010110010110001111001110100 +
b10001 .
b01000 /
b01011110111110101100011111001110 3
b10100010110010110001111001110100 4
#663000
1$
b00010 '
b10101001111100010110110100010001 (
1-
b00010 0
b10101001111100010110110100010001 1
#665000
0#
0,
#670000
1#
0$
1,
0-
b10101001111100010110110100010001 7
#671000
#672000
b00011 %
b00101 &
b10101101011011110010100000000011 *
b11110100110001111101110101011011 +
b00011 .
b00101 /
b10101101011011110010100000000011 3
b11110100110001111101110101011011 4
#673000
1$
b10111 '
b00011110110010110001110010000111 (
1-
b10111 0
b00011110110010110001110010000111 1
#675000
0#
0,
#680000
1#
0$
1,
0-
b00011110110010110001110010000111 L
#681000
#682000
b10010 %
b00001 &
b00010000100100101111111101110111 *
b00111101111110110101101010000000 +
b10010 .
b00001 /
b00010000100100101111111101110111 3
b00111101111110110101101010000000 4
#683000
1$
b01111 '
b11010000100010000111110001111101 (
1-
b01111 0
b11010000100010000111110001111101 1
#685000
0#
0,
#690000
1#
0$
1,
0-
b11010000100010000111110001111101 D
#691000
#692000
b10101 %
b01011 &
b11010010111000001010000100100011 *
b00000000000000000000000000000000 +
b10101 .
b01011 /
b11010010111000001010000100100011 3
b00000000000000000000000000000000 4
#693000
1$
b01100 '
b11101000101111011001110101011100 (
1-
b01100 0
b11101000101111011001110101011100 1
#695000
0#
0,
#700000
1#
0$
1,
0-
b11101000101111011001110101011100 A
#701000
#702000
b10000 %
b00011 &
b00000000000000000000000000000000 *
b10101101011011110010100000000011 +
b10000 .
b00011 /
b00000000000000000000000000000000 3
b10101101011011110010100000000011 4
#703000
1$
b10101 '
b10111111101101101000001101010000 (
1-
b10101 0
b10111111101101101000001101010000 1
#705000
0#
0,
#710000
1#
0$
1,
0-
b10111111101101101000001101010000 J
#711000
#712000
b11111 %
b01100 &
b10011010110101011001010010101110 *
b11101000101111011001110101011100 +
b11111 .
b01100 /
b10011010110101011001010010101110 3
b11101000101111011001110101011100 4
#713000
1$
b00001 '
b00000000000010001010010100000010 (
1-
b00001 0
b00000000000010001010010100000010 1
#715000
0#
0,
#720000
1#
0$
1,
0-
b00000000000010001010010100000010 6
#721000
#722000
b10111 %
b11000 &
b00011110110010110001110010000111 *
b01000100100101110110111111100010 +
b10111 .
b11000 /
b00011110110010110001110010000111 3
b01000100100101110110111111100010 4
#723000
1$
b00100 '
b10000010111111101011100111101010 (
1-
b00100 0
b10000010111111101011100111101010 1
#725000
0#
0,
#730000
1#
0$
1,
0-
b10000010111111101011100111101010 9
#731000
#732000
b11011 %
b10100 &
b01110111000101001010001000101100 *
b00000000000000000000000000000000 +
b11011 .
b10100 /
b01110111000101001010001000101100 3
b00000000000000000000000000000000 4
#733000
1$
b00011 '
b00101011000000000111111011101100 (
1-
b00011 0
b00101011000000000111111011101100 1
#735000
0#
0,
#740000
1#
0$
1,
0-
b00101011000000000111111011101100 8
#741000
