design/alu.sv
`timescale 1ns/1ps

module alu (
    input logic [31:0] alu_control,
    input logic [31:0] operand1,
    input logic [31:0] operand2,
    input logic [4:0] shamt,

    output logic [31:0] alu_result
);

typedef enum {ALU_ADD, ALU_SUB, ALU_AND, ALU_OR, ALU_XOR} alu_control_t;

wire logic [4:0] shamt = operand2[4:0];

always_comb begin
    case (alu_control)
        // ADD STUFF
        ALU_ADD : alu_result = operand1 + operand2;
        ALU_SUB : alu_result = operand1 + (~operand2 + 1'b1);
        ALU_AND : alu_result = operand1 & operand2;
        ALU_OR : alu_result = operand1 | operand2;
        ALU_XOR : alu_result = operand1 ^ operand2;
        default : alu_result = 32'd0;
    endcase
end
    
endmodule

tb/dump.vcd
$version Generated by VerilatedVcd $end
$timescale 1ps $end
 $scope module $rootio $end
  $var wire 32 # alu_control [31:0] $end
  $var wire 32 $ operand1 [31:0] $end
  $var wire 32 % operand2 [31:0] $end
  $var wire 32 & alu_result [31:0] $end
 $upscope $end
 $scope module alu $end
  $var wire 32 ' alu_control [31:0] $end
  $var wire 32 ( operand1 [31:0] $end
  $var wire 32 ) operand2 [31:0] $end
  $var wire 32 * alu_result [31:0] $end
  $var wire 5 + shamt [4:0] $end
 $upscope $end
$enddefinitions $end


#0
b00000000000000000000000000000000 #
b00000000000000000000000000000000 $
b00000000000000000000000000000000 %
b00000000000000000000000000000000 &
b00000000000000000000000000000000 '
b00000000000000000000000000000000 (
b00000000000000000000000000000000 )
b00000000000000000000000000000000 *
b00000 +
#1000
b10001011011011110011111000110111 $
b10001000100000100010001101001110 %
b00010011111100010110000110000101 &
b10001011011011110011111000110111 (
b10001000100000100010001101001110 )
b00010011111100010110000110000101 *
b01110 +
#2000
b10110111011011001010001011101001 $
b11110000101111001100010101001010 %
b10101000001010010110100000110011 &
b10110111011011001010001011101001 (
b11110000101111001100010101001010 )
b10101000001010010110100000110011 *
b01010 +
#3000
b00110011010011000011000011011000 $
b10111100100110101010111000000110 %
b11101111111001101101111011011110 &
b00110011010011000011000011011000 (
b10111100100110101010111000000110 )
b11101111111001101101111011011110 *
b00110 +
#4000
b01111110010100001010111000000010 $
b11001101100100010110111101110111 %
b01001011111000100001110101111001 &
b01111110010100001010111000000010 (
b11001101100100010110111101110111 )
b01001011111000100001110101111001 *
b10111 +
#5000
b01100011100101101111001001011001 $
b00001111100111100001100111001010 %
b01110011001101010000110000100011 &
b01100011100101101111001001011001 (
b00001111100111100001100111001010 )
b01110011001101010000110000100011 *
b01010 +
#6000
b10010100111011011110010011011101 $
b00001010110010001010100011100001 %
b10011111101101101000110110111110 &
b10010100111011011110010011011101 (
b00001010110010001010100011100001 )
b10011111101101101000110110111110 *
b00001 +
#7000
b10111010111011000100101110110000 $
b00101010001101100100010000100001 %
b11100101001000101000111111010001 &
b10111010111011000100101110110000 (
b00101010001101100100010000100001 )
b11100101001000101000111111010001 *
#8000
b11101011001011110011110111110000 $
b10101100111110110000001001001010 %
b10011000001010100100000000111010 &
b11101011001011110011110111110000 (
b10101100111110110000001001001010 )
b10011000001010100100000000111010 *
b01010 +
#9000
b01111111010100110000101100011111 $
b11000000001011000101100100101111 %
b00111111011111110110010001001110 &
b01111111010100110000101100011111 (
b11000000001011000101100100101111 )
b00111111011111110110010001001110 *
b01111 +
#10000
b00111010111010111101110010000110 $
b00010110100110010000101001110010 %
b01010001100001001110011011111000 &
b00111010111010111101110010000110 (
b00010110100110010000101001110010 )
b01010001100001001110011011111000 *
b10010 +
#11000
b01001000100011000000110001001010 $
b00110101101110000100000101100001 %
b01111110010001000100110110101011 &
b01001000100011000000110001001010 (
b00110101101110000100000101100001 )
b01111110010001000100110110101011 *
b00001 +
#12000
b00111101110001110111001111111111 $
b00111000111110010111010100010100 %
b01110110110000001110100100010011 &
b00111101110001110111001111111111 (
b00111000111110010111010100010100 )
b01110110110000001110100100010011 *
b10100 +
#13000
b10100010101001111101111101101110 $
b01000111001001110011010111011110 %
b11101001110011110001010101001100 &
b10100010101001111101111101101110 (
b01000111001001110011010111011110 )
b11101001110011110001010101001100 *
b11110 +
#14000
b00000100111001001100111010101111 $
b10011011000111001100011100100010 %
b10100000000000011001010111010001 &
b00000100111001001100111010101111 (
b10011011000111001100011100100010 )
b10100000000000011001010111010001 *
b00010 +
#15000
b01101001001110101100010010000111 $
b00000000101100101111010011111110 %
b01101001111011011011100110000101 &
b01101001001110101100010010000111 (
b00000000101100101111010011111110 )
b01101001111011011011100110000101 *
b11110 +
#16000
b00111010010001000001000110111101 $
b10110110101000000001011000101000 %
b11110000111001000010011111100101 &
b00111010010001000001000110111101 (
b10110110101000000001011000101000 )
b11110000111001000010011111100101 *
b01000 +
#17000
b10100010011001111111010011110111 $
b01010011110101111101111001101001 %
b11110110001111111101001101100000 &
b10100010011001111111010011110111 (
b01010011110101111101111001101001 )
b11110110001111111101001101100000 *
b01001 +
#18000
b10101100110100100010100010001010 $
b00000100100001000101000110001011 %
b10110001010101100111101000010101 &
b10101100110100100010100010001010 (
b00000100100001000101000110001011 )
b10110001010101100111101000010101 *
b01011 +
#19000
b00111011011110000010000010100000 $
b11000101000010010010111100111110 %
b00000000100000010100111111011110 &
b00111011011110000010000010100000 (
b11000101000010010010111100111110 )
b00000000100000010100111111011110 *
b11110 +
#20000
b01100010011100111001100011010000 $
b10001000000111001010010001110010 %
b11101010100100000011110101000010 &
b01100010011100111001100011010000 (
b10001000000111001010010001110010 )
b11101010100100000011110101000010 *
b10010 +
#21000
b00000000100101011001000011001101 $
b01101011111111100010011010101100 %
b01101100100100111011011101111001 &
b00000000100101011001000011001101 (
b01101011111111100010011010101100 )
b01101100100100111011011101111001 *
b01100 +
#22000
b11011110111111111000101111111010 $
b01000001010111011001111010001111 %
b00100000010111010010101010001001 &
b11011110111111111000101111111010 (
b01000001010111011001111010001111 )
b00100000010111010010101010001001 *
b01111 +
#23000
b00010001010111111010111110101000 $
b10111101101010110110111110110100 %
b11001111000010110001111101011100 &
b00010001010111111010111110101000 (
b10111101101010110110111110110100 )
b11001111000010110001111101011100 *
b10100 +
#24000
b11111000110001011101110111111011 $
b10001011100111001010001100001011 %
b10000100011000101000000100000110 &
b11111000110001011101110111111011 (
b10001011100111001010001100001011 )
b10000100011000101000000100000110 *
b01011 +
#25000
b01001111110101010001010110100001 $
b00110100011010111100011110010001 %
b10000100010000001101110100110010 &
b01001111110101010001010110100001 (
b00110100011010111100011110010001 )
b10000100010000001101110100110010 *
b10001 +
#26000
b00011011011101111000001010000000 $
b11100101110011001000110000111110 %
b00000001010001000000111010111110 &
b00011011011101111000001010000000 (
b11100101110011001000110000111110 )
b00000001010001000000111010111110 *
b11110 +
#27000
b10000110001101110011000010010010 $
b01010010011110011100111010101100 %
b11011000101100001111111100111110 &
b10000110001101110011000010010010 (
b01010010011110011100111010101100 )
b11011000101100001111111100111110 *
b01100 +
#28000
b00101011100110111110101010000110 $
b11011110111110011001001101101011 %
b00001010100101010111110111110001 &
b00101011100110111110101010000110 (
b11011110111110011001001101101011 )
b00001010100101010111110111110001 *
b01011 +
#29000
b00110101000001001110001110101111 $
b01000001001101001010001001100010 %
b01110110001110011000011000010001 &
b00110101000001001110001110101111 (
b01000001001101001010001001100010 )
b01110110001110011000011000010001 *
b00010 +
#30000
b00000001110100010101110101010011 $
b01011001100011001100010011001111 %
b01011011010111100010001000100010 &
b00000001110100010101110101010011 (
b01011001100011001100010011001111 )
b01011011010111100010001000100010 *
b01111 +
#31000
b01111010100111110111100111010001 $
b00010001001001100111101110110111 %
b10001011110001011111010110001000 &
b01111010100111110111100111010001 (
b00010001001001100111101110110111 )
b10001011110001011111010110001000 *
b10111 +
#32000
b10111011110100100001101100011001 $
b11100110111011110100101011100100 %
b10100010110000010110010111111101 &
b10111011110100100001101100011001 (
b11100110111011110100101011100100 )
b10100010110000010110010111111101 *
b00100 +
#33000
b10100011010000100000010001001101 $
b11011101111011001111101011000001 %
b10000001001011101111111100001110 &
b10100011010000100000010001001101 (
b11011101111011001111101011000001 )
b10000001001011101111111100001110 *
b00001 +
#34000
b00111010101101100001000110001000 $
b01111100110110110000000100101101 %
b10110111100100010001001010110101 &
b00111010101101100001000110001000 (
b01111100110110110000000100101101 )
b10110111100100010001001010110101 *
b01101 +
#35000
b11110010100001011001001001101111 $
b01110010011100100101000000010100 %
b01100100111101111110001010000011 &
b11110010100001011001001001101111 (
b01110010011100100101000000010100 )
b01100100111101111110001010000011 *
b10100 +
#36000
b00110101111100100000000000101001 $
b01001110011111011111101110101001 %
b10000100011011111111101111010010 &
b00110101111100100000000000101001 (
b01001110011111011111101110101001 )
b10000100011011111111101111010010 *
b01001 +
#37000
b00111111000011111001010100000101 $
b01110011101000111000011010000001 %
b10110010101100110001101110000110 &
b00111111000011111001010100000101 (
b01110011101000111000011010000001 )
b10110010101100110001101110000110 *
b00001 +
#38000
b01011100001111101100001111110110 $
b11101111111110001011101000001110 %
b01001100001101110111111000000100 &
b01011100001111101100001111110110 (
b11101111111110001011101000001110 )
b01001100001101110111111000000100 *
b01110 +
#39000
b10010110100110101110111001000010 $
b10100011011110111010110001100100 %
b00111010000101101001101010100110 &
b10010110100110101110111001000010 (
b10100011011110111010110001100100 )
b00111010000101101001101010100110 *
b00100 +
#40000
b11101010001111000000001010010000 $
b01010100010111001001000100010110 %
b00111110100110001001001110100110 &
b11101010001111000000001010010000 (
b01010100010111001001000100010110 )
b00111110100110001001001110100110 *
b10110 +
#41000
b01010111000010101111110111110001 $
b01101111100110110110100011101011 %
b11000110101001100110011011011100 &
b01010111000010101111110111110001 (
b01101111100110110110100011101011 )
b11000110101001100110011011011100 *
b01011 +
#42000
b10100100110111011001100000100011 $
b00010000001001001001001111010100 %
b10110101000000100010101111110111 &
b10100100110111011001100000100011 (
b00010000001001001001001111010100 )
b10110101000000100010101111110111 *
b10100 +
#43000
b11011010100010000010100011111011 $
b10001010100100011010001000010100 %
b01100101000110011100101100001111 &
b11011010100010000010100011111011 (
b10001010100100011010001000010100 )
b01100101000110011100101100001111 *
#44000
b00011100001110100000101110100101 $
b01011110010101100001000111001000 %
b01111010100100000001110101101101 &
b00011100001110100000101110100101 (
b01011110010101100001000111001000 )
b01111010100100000001110101101101 *
b01000 +
#45000
b11000010110100011000001110100011 $
b01101100001010011111111011110000 %
b00101110111110111000001010010011 &
b11000010110100011000001110100011 (
b01101100001010011111111011110000 )
b00101110111110111000001010010011 *
b10000 +
#46000
b11100110110100000110001101001100 $
b00000001001000101110101110111111 %
b11100111111100110100111100001011 &
b11100110110100000110001101001100 (
b00000001001000101110101110111111 )
b11100111111100110100111100001011 *
b11111 +
#47000
b00000101010010111011010111011101 $
b01001001111100111111011011110010 %
b01001111001111111010110011001111 &
b00000101010010111011010111011101 (
b01001001111100111111011011110010 )
b01001111001111111010110011001111 *
b10010 +
#48000
b01011110011000010000110111000001 $
b00010110000100000000111100001100 %
b01110100011100010001110011001101 &
b01011110011000010000110111000001 (
b00010110000100000000111100001100 )
b01110100011100010001110011001101 *
b01100 +
#49000
b01100000000111010110001110111111 $
b01110010000110110111001010110101 %
b11010010001110001101011001110100 &
b01100000000111010110001110111111 (
b01110010000110110111001010110101 )
b11010010001110001101011001110100 *
b10101 +
#50000
b00111111111010000101011101110011 $
b11100101110100001001011100111111 %
b00100101101110001110111010110010 &
b00111111111010000101011101110011 (
b11100101110100001001011100111111 )
b00100101101110001110111010110010 *
b11111 +
#51000
b10001011100011110000111111001101 $
b10110000010001000011001111100000 %
b00111011110100110100001110101101 &
b10001011100011110000111111001101 (
b10110000010001000011001111100000 )
b00111011110100110100001110101101 *
b00000 +
#52000
b01010011011111100110011001000011 $
b11100100110101101000111010110010 %
b00111000010101001111010011110101 &
b01010011011111100110011001000011 (
b11100100110101101000111010110010 )
b00111000010101001111010011110101 *
b10010 +
#53000
b00111001100011100011111101001011 $
b01000010111000000001010100100110 %
b01111100011011100101010001110001 &
b00111001100011100011111101001011 (
b01000010111000000001010100100110 )
b01111100011011100101010001110001 *
b00110 +
#54000
b01001001100000100010010101010011 $
b01011001110001110110011011011001 %
b10100011010010011000110000101100 &
b01001001100000100010010101010011 (
b01011001110001110110011011011001 )
b10100011010010011000110000101100 *
b11001 +
#55000
b11111011101111010111000100101000 $
b00011111011101100100111001000001 %
b00011011001100111011111101101001 &
b11111011101111010111000100101000 (
b00011111011101100100111001000001 )
b00011011001100111011111101101001 *
b00001 +
#56000
b00101111110100111001000001010000 $
b01110110000011010111001011001111 %
b10100101111000010000001100011111 &
b00101111110100111001000001010000 (
b01110110000011010111001011001111 )
b10100101111000010000001100011111 *
b01111 +
#57000
b11100101011111001100100000111100 $
b00110000011100101000010001110110 %
b00010101111011110100110010110010 &
b11100101011111001100100000111100 (
b00110000011100101000010001110110 )
b00010101111011110100110010110010 *
b10110 +
#58000
b01010010110100111001100000111111 $
b10010010101000110111011101011010 %
b11100101011101110000111110011001 &
b01010010110100111001100000111111 (
b10010010101000110111011101011010 )
b11100101011101110000111110011001 *
b11010 +
#59000
b00011001111101111001111100010101 $
b11110010011011111001110001000100 %
b00001100011001110011101101011001 &
b00011001111101111001111100010101 (
b11110010011011111001110001000100 )
b00001100011001110011101101011001 *
b00100 +
#60000
b11101101100010010011010111010100 $
b10110110111111000010110010011010 %
b10100100100001010110001001101110 &
b11101101100010010011010111010100 (
b10110110111111000010110010011010 )
b10100100100001010110001001101110 *
b11010 +
#61000
b10010110100100110111000110000011 $
b11000000001101010100000111010111 %
b01010110110010001011001101011010 &
b10010110100100110111000110000011 (
b11000000001101010100000111010111 )
b01010110110010001011001101011010 *
b10111 +
#62000
b11111011111001101110110011110011 $
b00110111101111101011011000011101 %
b00110011101001011010001100010000 &
b11111011111001101110110011110011 (
b00110111101111101011011000011101 )
b00110011101001011010001100010000 *
b11101 +
#63000
b01100010101101110000101110110100 $
b00111011010100100001110110000101 %
b10011110000010010010100100111001 &
b01100010101101110000101110110100 (
b00111011010100100001110110000101 )
b10011110000010010010100100111001 *
b00101 +
#64000
b10100110000010101010000100100010 $
b10100001111000111101011111101111 %
b01000111111011100111100100010001 &
b10100110000010101010000100100010 (
b10100001111000111101011111101111 )
b01000111111011100111100100010001 *
b01111 +
#65000
b01110000110011001110110001010011 $
b00000100111000110010101101001001 %
b01110101101100000001011110011100 &
b01110000110011001110110001010011 (
b00000100111000110010101101001001 )
b01110101101100000001011110011100 *
b01001 +
#66000
b10110111010000011101101111010010 $
b11111000000110000110110100000011 %
b10101111010110100100100011010101 &
b10110111010000011101101111010010 (
b11111000000110000110110100000011 )
b10101111010110100100100011010101 *
b00011 +
#67000
b01110011010111101111011010101101 $
b00111110101011011001101110110000 %
b10110010000011001001001001011101 &
b01110011010111101111011010101101 (
b00111110101011011001101110110000 )
b10110010000011001001001001011101 *
b10000 +
#68000
b00001110110001000000011101111111 $
b00110000101001010011110110110101 %
b00111111011010010100010100110100 &
b00001110110001000000011101111111 (
b00110000101001010011110110110101 )
b00111111011010010100010100110100 *
b10101 +
#69000
b01011011000111001011011011100001 $
b11101100000010111100010101000101 %
b01000111001010000111110000100110 &
b01011011000111001011011011100001 (
b11101100000010111100010101000101 )
b01000111001010000111110000100110 *
b00101 +
#70000
b11110011010010110011111001001000 $
b00101100110101110101010110111111 %
b00100000001000101001010000000111 &
b11110011010010110011111001001000 (
b00101100110101110101010110111111 )
b00100000001000101001010000000111 *
b11111 +
#71000
b00101111111110101000001000000011 $
b00110100101111110011011100010000 %
b01100100101110011011100100010011 &
b00101111111110101000001000000011 (
b00110100101111110011011100010000 )
b01100100101110011011100100010011 *
b10000 +
#72000
b11101110000101101011011110100000 $
b00000100010101100001100010001110 %
b11110010011011001101000000101110 &
b11101110000101101011011110100000 (
b00000100010101100001100010001110 )
b11110010011011001101000000101110 *
b01110 +
#73000
b10111110101010110010111111000110 $
b11000111101000100001100010001011 %
b10000110010011010100100001010001 &
b10111110101010110010111111000110 (
b11000111101000100001100010001011 )
b10000110010011010100100001010001 *
b01011 +
#74000
b01010001000001000111101000001010 $
b10010101101101110000101011000111 %
b11100110101110111000010011010001 &
b01010001000001000111101000001010 (
b10010101101101110000101011000111 )
b11100110101110111000010011010001 *
b00111 +
#75000
b00100101001011110001111100010010 $
b00011101101000110111111110010110 %
b01000010110100101001111010101000 &
b00100101001011110001111100010010 (
b00011101101000110111111110010110 )
b01000010110100101001111010101000 *
b10110 +
#76000
b01101101100001111110100011111101 $
b01111101001010101111010101101111 %
b11101010101100101101111001101100 &
b01101101100001111110100011111101 (
b01111101001010101111010101101111 )
b11101010101100101101111001101100 *
b01111 +
#77000
b00101110001101110110111111100001 $
b01100001011011010111001011001100 %
b10001111101001001110001010101101 &
b00101110001101110110111111100001 (
b01100001011011010111001011001100 )
b10001111101001001110001010101101 *
b01100 +
#78000
b00111100111010010011100001001000 $
b10111000010110001101111000001100 %
b11110101010000100001011001010100 &
b00111100111010010011100001001000 (
b10111000010110001101111000001100 )
b11110101010000100001011001010100 *
#79000
b01100000011001000001011010110001 $
b10010000010010101101100000110110 %
b11110000101011101110111011100111 &
b01100000011001000001011010110001 (
b10010000010010101101100000110110 )
b11110000101011101110111011100111 *
b10110 +
#80000
b11100111111100111111110101000001 $
b10100101011001111001110101010011 %
b10001101010110111001101010010100 &
b11100111111100111111110101000001 (
b10100101011001111001110101010011 )
b10001101010110111001101010010100 *
b10011 +
#81000
b11101100000101001101111100101110 $
b01101111011000001000100000010101 %
b01011011011101010110011101000011 &
b11101100000101001101111100101110 (
b01101111011000001000100000010101 )
b01011011011101010110011101000011 *
b10101 +
#82000
b11110011101000101101011010101101 $
b10011111111001100111101111000000 %
b10010011100010010101001001101101 &
b11110011101000101101011010101101 (
b10011111111001100111101111000000 )
b10010011100010010101001001101101 *
b00000 +
#83000
b01010101011111100000111111111111 $
b10001111010011010100111100011011 %
b11100100110010110101111100011010 &
b01010101011111100000111111111111 (
b10001111010011010100111100011011 )
b11100100110010110101111100011010 *
b11011 +
#84000
b11110101010100100011101100111110 $
b01010011111010110100000011000110 %
b01001001001111010111110000000100 &
b11110101010100100011101100111110 (
b01010011111010110100000011000110 )
b01001001001111010111110000000100 *
b00110 +
#85000
b10011010011110001100100100100101 $
b00110000001101010001001110010011 %
b11001010101011011101110010111000 &
b10011010011110001100100100100101 (
b00110000001101010001001110010011 )
b11001010101011011101110010111000 *
b10011 +
#86000
b01001000110000100010000001111001 $
b01101110010011011011111111001111 %
b10110111000011111110000001001000 &
b01001000110000100010000001111001 (
b01101110010011011011111111001111 )
b10110111000011111110000001001000 *
b01111 +
#87000
b00111110011010111111111111100100 $
b01010000111011000110001110011001 %
b10001111010110000110001101111101 &
b00111110011010111111111111100100 (
b01010000111011000110001110011001 )
b10001111010110000110001101111101 *
b11001 +
#88000
b10011101000000110101000010011111 $
b11110101000111100010101011011000 %
b10010010001000010111101101110111 &
b10011101000000110101000010011111 (
b11110101000111100010101011011000 )
b10010010001000010111101101110111 *
b11000 +
#89000
b10101111010010100001000101011001 $
b01010111010000010010110100010110 %
b00000110100010110011111001101111 &
b10101111010010100001000101011001 (
b01010111010000010010110100010110 )
b00000110100010110011111001101111 *
b10110 +
#90000
b11001000101010111100010000101110 $
b00010010100010000010111001110101 %
b11011011001100111111001010100011 &
b11001000101010111100010000101110 (
b00010010100010000010111001110101 )
b11011011001100111111001010100011 *
b10101 +
#91000
b11101100011111110011110110110001 $
b10010101111000111000011111100101 %
b10000010011000101100010110010110 &
b11101100011111110011110110110001 (
b10010101111000111000011111100101 )
b10000010011000101100010110010110 *
b00101 +
#92000
b01110110011000000011000010011011 $
b10011111010000001011101111010010 %
b00010101101000001110110001101101 &
b01110110011000000011000010011011 (
b10011111010000001011101111010010 )
b00010101101000001110110001101101 *
b10010 +
#93000
b00011001101110001111001110101010 $
b11011100010100000110110011111100 %
b11110110000010010110000010100110 &
b00011001101110001111001110101010 (
b11011100010100000110110011111100 )
b11110110000010010110000010100110 *
b11100 +
#94000
b00011011100011010011010011011110 $
b10110010100110101010110111001111 %
b11001110001001111110001010101101 &
b00011011100011010011010011011110 (
b10110010100110101010110111001111 )
b11001110001001111110001010101101 *
b01111 +
#95000
b01110001101100100000100011100101 $
b00000101110101011010100110000001 %
b01110111100001111011001001100110 &
b01110001101100100000100011100101 (
b00000101110101011010100110000001 )
b01110111100001111011001001100110 *
b00001 +
#96000
b01001101011010101101001011100110 $
b00011100101111111100100001010100 %
b01101010001010101001101100111010 &
b01001101011010101101001011100110 (
b00011100101111111100100001010100 )
b01101010001010101001101100111010 *
b10100 +
#97000
b11000110110000000110101010100001 $
b10001011101100011000010001110011 %
b01010010011100011110111100010100 &
b11000110110000000110101010100001 (
b10001011101100011000010001110011 )
b01010010011100011110111100010100 *
b10011 +
#98000
b00000000111101011010111111101110 $
b11111110011001001111010101101001 %
b11111111010110101010010101010111 &
b00000000111101011010111111101110 (
b11111110011001001111010101101001 )
b11111111010110101010010101010111 *
b01001 +
#99000
b00101010011010001011010110000100 $
b00101011011011011100001100011101 %
b01010101110101100111100010100001 &
b00101010011010001011010110000100 (
b00101011011011011100001100011101 )
b01010101110101100111100010100001 *
b11101 +
#100000
b01000011001000010111110110111010 $
b00110100100101000000101111011010 %
b01110111101101011000100110010100 &
b01000011001000010111110110111010 (
b00110100100101000000101111011010 )
b01110111101101011000100110010100 *
b11010 +
#101000
b00101100000101110011000111101010 $
b11010111101011010111110101101010 %
b00000011110001001010111101010100 &
b00101100000101110011000111101010 (
b11010111101011010111110101101010 )
b00000011110001001010111101010100 *
b01010 +
#102000
b00101000111100111101001010010111 $
b10110001101000001000000100111101 %
b11011010100101000101001111010100 &
b00101000111100111101001010010111 (
b10110001101000001000000100111101 )
b11011010100101000101001111010100 *
b11101 +
#103000
b01111000110010010110011100011010 $
b11111100111100110100110110111110 %
b01110101101111001011010011011000 &
b01111000110010010110011100011010 (
b11111100111100110100110110111110 )
b01110101101111001011010011011000 *
b11110 +
#104000
b11011010011100110001101001001011 $
b10100101101111000110010000110001 %
b10000000001011110111111001111100 &
b11011010011100110001101001001011 (
b10100101101111000110010000110001 )
b10000000001011110111111001111100 *
b10001 +
#105000
b01100100111101010001100110000000 $
b01010011000011010110101100110011 %
b10111000000000101000010010110011 &
b01100100111101010001100110000000 (
b01010011000011010110101100110011 )
b10111000000000101000010010110011 *
b10011 +
#106000
b00111110101111001000011111011010 $
b11010110011000110010010001001010 %
b00010101000111111010110000100100 &
b00111110101111001000011111011010 (
b11010110011000110010010001001010 )
b00010101000111111010110000100100 *
b01010 +
#107000
b00011010101011111011010011000101 $
b11000000101010011010110010011100 %
b11011011010110010110000101100001 &
b00011010101011111011010011000101 (
b11000000101010011010110010011100 )
b11011011010110010110000101100001 *
b11100 +
#108000
b00111011001001101111000001100011 $
b11101010100110000100110110001001 %
b00100101101111110011110111101100 &
b00111011001001101111000001100011 (
b11101010100110000100110110001001 )
b00100101101111110011110111101100 *
b01001 +
#109000
b01110110100110100001011000111000 $
b01000110111101111111101110011111 %
b10111101100100100001000111010111 &
b01110110100110100001011000111000 (
b01000110111101111111101110011111 )
b10111101100100100001000111010111 *
b11111 +
#110000
b00101101011000010000010111000010 $
b11110001000101111000100010010000 %
b00011110011110001000111001010010 &
b00101101011000010000010111000010 (
b11110001000101111000100010010000 )
b00011110011110001000111001010010 *
b10000 +
#111000
b11001110000010110011110001101111 $
b01010010011001100101111110001010 %
b00100000011100011001101111111001 &
b11001110000010110011110001101111 (
b01010010011001100101111110001010 )
b00100000011100011001101111111001 *
b01010 +
#112000
b00001111100000100111110001100101 $
b00110100011111011101101001111111 %
b01000100000000000101011011100100 &
b00001111100000100111110001100101 (
b00110100011111011101101001111111 )
b01000100000000000101011011100100 *
b11111 +
#113000
b11110000101100100010001101101000 $
b10010011101000000110000110110110 %
b10000100010100101000010100011110 &
b11110000101100100010001101101000 (
b10010011101000000110000110110110 )
b10000100010100101000010100011110 *
b10110 +
#114000
b00101111011001001101100111010100 $
b10100100111011001111111111100010 %
b11010100010100011101100110110110 &
b00101111011001001101100111010100 (
b10100100111011001111111111100010 )
b11010100010100011101100110110110 *
b00010 +
#115000
b01101110101010010111100010101100 $
b01001111001111101100001010111010 %
b10111101111010000011101101100110 &
b01101110101010010111100010101100 (
b01001111001111101100001010111010 )
b10111101111010000011101101100110 *
b11010 +
#116000
b01100101011010100100110011101000 $
b10001010000010101000001100110011 %
b11101111011101001101000000011011 &
b01100101011010100100110011101000 (
b10001010000010101000001100110011 )
b11101111011101001101000000011011 *
b10011 +
#117000
b00110011000010000110100100011111 $
b00001111000001010000000001001000 %
b01000010000011010110100101100111 &
b00110011000010000110100100011111 (
b00001111000001010000000001001000 )
b01000010000011010110100101100111 *
b01000 +
#118000
b11010001011101111010110001011100 $
b00000001111111001100100000010001 %
b11010011011101000111010001101101 &
b11010001011101111010110001011100 (
b00000001111111001100100000010001 )
b11010011011101000111010001101101 *
b10001 +
#119000
b01100010000110101100101110100000 $
b11100010011011100110001110110100 %
b01000100100010010010111101010100 &
b01100010000110101100101110100000 (
b11100010011011100110001110110100 )
b01000100100010010010111101010100 *
b10100 +
#120000
b11010100100110000011100011000000 $
b00100010100110010100010110100110 %
b11110111001100010111111001100110 &
b11010100100110000011100011000000 (
b00100010100110010100010110100110 )
b11110111001100010111111001100110 *
b00110 +
#121000
b00011000000100110110100100001010 $
b00010111011000000000000101110100 %
b00101111011100110110101001111110 &
b00011000000100110110100100001010 (
b00010111011000000000000101110100 )
b00101111011100110110101001111110 *
b10100 +
#122000
b01111001110101011001110111000011 $
b11010000111001000000100011000111 %
b01001010101110011010011010001010 &
b01111001110101011001110111000011 (
b11010000111001000000100011000111 )
b01001010101110011010011010001010 *
b00111 +
#123000
b11011000000101000011111111100011 $
b00001011010000000110110111000111 %
b11100011010101001010110110101010 &
b11011000000101000011111111100011 (
b00001011010000000110110111000111 )
b11100011010101001010110110101010 *
#124000
b00110110110101111011011001001000 $
b01101000010100010100111101011011 %
b10011111001010010000010110100011 &
b00110110110101111011011001001000 (
b01101000010100010100111101011011 )
b10011111001010010000010110100011 *
b11011 +
#125000
b11101101010001110010101110110001 $
b00011101110001011000101000001011 %
b00001011000011001011010110111100 &
b11101101010001110010101110110001 (
b00011101110001011000101000001011 )
b00001011000011001011010110111100 *
b01011 +
#126000
b10110001001111001001000111000010 $
b00111010010110101100011111001001 %
b11101011100101110101100110001011 &
b10110001001111001001000111000010 (
b00111010010110101100011111001001 )
b11101011100101110101100110001011 *
b01001 +
#127000
b10010010001101011011000100101001 $
b10111101001110001101111101011101 %
b01001111011011101001000010000110 &
b10010010001101011011000100101001 (
b10111101001110001101111101011101 )
b01001111011011101001000010000110 *
b11101 +
#128000
b01001000111000100101000001111000 $
b10100110111110000110111110000111 %
b11101111110110101011111111111111 &
b01001000111000100101000001111000 (
b10100110111110000110111110000111 )
b11101111110110101011111111111111 *
b00111 +
#129000
b11011011101001010001000011110011 $
b11101110110110101110110010001001 %
b11001010011111111111110101111100 &
b11011011101001010001000011110011 (
b11101110110110101110110010001001 )
b11001010011111111111110101111100 *
b01001 +
#130000
b10111000110010011101001101100111 $
b11001011110000111001010110110110 %
b10000100100011010110100100011101 &
b10111000110010011101001101100111 (
b11001011110000111001010110110110 )
b10000100100011010110100100011101 *
b10110 +
#131000
b10101010000101000100101000001101 $
b11110010110110011010111100011000 %
b10011100111011011111100100100101 &
b10101010000101000100101000001101 (
b11110010110110011010111100011000 )
b10011100111011011111100100100101 *
b11000 +
#132000
b01100100011101101100110000001010 $
b10100100011000100101010001000011 %
b00001000110110010010000001001101 &
b01100100011101101100110000001010 (
b10100100011000100101010001000011 )
b00001000110110010010000001001101 *
b00011 +
#133000
b11001100001111100010100001011110 $
b11111010011011101001110010110011 %
b11000110101011001100010100010001 &
b11001100001111100010100001011110 (
b11111010011011101001110010110011 )
b11000110101011001100010100010001 *
b10011 +
#134000
b00010010101101000100111010101111 $
b00100001000011101110111000110000 %
b00110011110000110011110011011111 &
b00010010101101000100111010101111 (
b00100001000011101110111000110000 )
b00110011110000110011110011011111 *
b10000 +
#135000
b11110111100111000011101100100000 $
b01000010010101100111011011000001 %
b00111001111100101011000111100001 &
b11110111100111000011101100100000 (
b01000010010101100111011011000001 )
b00111001111100101011000111100001 *
b00001 +
#136000
b11101101101011110100111110011110 $
b10011100100000101000010110001101 %
b10001010001100011101010100101011 &
b11101101101011110100111110011110 (
b10011100100000101000010110001101 )
b10001010001100011101010100101011 *
b01101 +
#137000
b11101011001110011010001011000100 $
b01101110001011010100011011010111 %
b01011001011001101110100110011011 &
b11101011001110011010001011000100 (
b01101110001011010100011011010111 )
b01011001011001101110100110011011 *
b10111 +
#138000
b11011011000000111101010011100100 $
b00111100100000011010111100100001 %
b00010111100001011000010000000101 &
b11011011000000111101010011100100 (
b00111100100000011010111100100001 )
b00010111100001011000010000000101 *
b00001 +
#139000
b01001010100001011001111110001010 $
b11000110001101010101011111010110 %
b00010000101110101111011101100000 &
b01001010100001011001111110001010 (
b11000110001101010101011111010110 )
b00010000101110101111011101100000 *
b10110 +
#140000
b01110000110101110110100100001111 $
b01011101001111010101001110101011 %
b11001110000101001011110010111010 &
b01110000110101110110100100001111 (
b01011101001111010101001110101011 )
b11001110000101001011110010111010 *
b01011 +
#141000
b00110110001001110100110101111101 $
b10101100000100110100101100011110 %
b11100010001110101001100010011011 &
b00110110001001110100110101111101 (
b10101100000100110100101100011110 )
b11100010001110101001100010011011 *
b11110 +
#142000
b01110110001101100010111110100010 $
b01000100001110101111001010101011 %
b10111010011100010010001001001101 &
b01110110001101100010111110100010 (
b01000100001110101111001010101011 )
b10111010011100010010001001001101 *
b01011 +
